{
  "bands": [
    {
      "id": "1bb16e9cb667084ce5a86f766d19d6f8",
      "name": "Then Comes Silence",
      "country": "S",
      "genre": "Gothic",
      "description": "Rock band"
    },
    {
      "id": "e8aa179ac2877d19f2fb242445036f84",
      "name": "Nouvelle Vague",
      "country": "F",
      "genre": "New Wave",
      "description": "Band"
    },
    {
      "id": "e29debecede17e5c0e7f030e0cc2f9a1",
      "name": "Skynd",
      "country": "AUS",
      "genre": "Industrial",
      "description": "Rock band"
    },
    {
      "id": "d5a5ca83f36b3bb6d201d4b1974b0b1a",
      "name": "Alphaville",
      "country": "D",
      "genre": "Synthpop",
      "description": "Pop band"
    },
    {
      "id": "4781ac9273d3335229ca90e8e00a1c71",
      "name": "Kite",
      "country": "S",
      "genre": "Synthpop",
      "description": "Pop group"
    },
    {
      "id": "f470592b0d38e198b70915bb4a05156b",
      "name": "Skelesys",
      "country": "D"
    },
    {
      "id": "f74ee7f89540fcc53f4b12b82cc42025",
      "name": "VVV [TrippinYou]",
      "country": "E"
    },
    {
      "id": "90928c6e169c17889b85fbe546457cf2",
      "name": "Selofan",
      "country": "GR"
    },
    {
      "id": "84b0318f8f015ba67aff86c211d2fcd8",
      "name": "Rue Oberkampf",
      "country": "D"
    },
    {
      "id": "689e88226f2d0027b679be5b3f1e421e",
      "name": "Labyrinth Ear",
      "country": "UK",
      "genre": "Electronic",
      "description": "Electronic duo"
    },
    {
      "id": "273c0de9551279a38a2ca50cb65c467c",
      "name": "Chainreactor",
      "country": "D"
    },
    {
      "id": "bd7fbdd6d4b03e6bce080d78fc575a22",
      "name": "Antibody",
      "country": "D"
    },
    {
      "id": "c126b3dbd774d72af2d51cdc0e832a07",
      "name": "Basszilla",
      "country": "D",
      "genre": "Artist",
      "description": "Musical artist"
    },
    {
      "id": "efee29522a06e60ec0a3e9c1e71f6ece",
      "name": "Eisenfunk",
      "country": "D",
      "genre": "EBM",
      "description": "Musical band"
    },
    {
      "id": "95f4ca3978931050c272981bd9116562",
      "name": "Noisuf-X",
      "country": "D",
      "genre": "Artist",
      "description": "Musical artist"
    },
    {
      "id": "b64884a0464d33488a31b8d3379eb3ff",
      "name": "Ventus Infecto- Brunnenbühne"
    },
    {
      "id": "c4782c02d2b8f5cff0fb06a1f253322a",
      "name": "Schwertspiel der Nordmänner- Brunnenbühne"
    },
    {
      "id": "79dbf50acd5819a5d7102cb9100d3cbe",
      "name": "Totus Gaudeo",
      "country": "D"
    },
    {
      "id": "09a9318508da52652852638eacbf39b4",
      "name": "Jungfrauenversteigerung- Brunnenbühne"
    },
    {
      "id": "4fe2356b10918b2cc29ba0ef7463a484",
      "name": "Mythemia",
      "country": "D"
    },
    {
      "id": "0f3adc8652c99ef33b3f945e29a0ac60",
      "name": "Fakir-Gaukeley– Brunnenbühne"
    },
    {
      "id": "13d38c86b45c92bc250fbfb96f0ccc89",
      "name": "Mila Mar",
      "country": "D",
      "genre": "Band",
      "description": "Musical band"
    },
    {
      "id": "c75d4ba31f3b96b5a6647cb58620d4a1",
      "name": "Schildwall-Kampf- Brunnenbühne"
    },
    {
      "id": "6ea6abfda82464e53a03a0c8a5c354ed",
      "name": "Coppelius",
      "country": "D",
      "genre": "Metal",
      "description": "Band"
    },
    {
      "id": "c989e5e42db682b1a5d0fc1cdf630bf4",
      "name": "Herold Schlemihl- Brunnenbühne"
    },
    {
      "id": "47a087cd05cd1ae463d66265384c4fa8",
      "name": "Gaukeley - Brunnenbühne"
    },
    {
      "id": "97d64296e472cacc626e54fbc933e665",
      "name": "Nytt Land",
      "country": "RUS",
      "genre": "Folk",
      "description": "Band"
    },
    {
      "id": "47a9cfcd95a53206e25acb64767e205f",
      "name": "Flammen im Zwielicht Feuerspektakel- Heidenbühne"
    },
    {
      "id": "cbc4fcab7a696e9e8eca061ce20f70bd",
      "name": "Incirrina",
      "country": "GR"
    },
    {
      "id": "f091dc80f3499920c4ae7b263592d06d",
      "name": "Ships In The Night",
      "country": "USA"
    },
    {
      "id": "db83bbe4cffc2097fb1b83c23926c185",
      "name": "Corlyx",
      "country": "UK"
    },
    {
      "id": "c641e02e5ddbe82589cbebbe9bb2ed03",
      "name": "Aux Animaux",
      "country": "S"
    },
    {
      "id": "4d32db1f0da7bc8aa8baa688424dee8b",
      "name": "Noelia Sarris Gothic Piano",
      "country": "ARG"
    },
    {
      "id": "38c91565571c7eba657528a02d57affd",
      "name": "Ruined Conflict",
      "country": "USA"
    },
    {
      "id": "ee20998fd5da6460ec33d4c1dac0efd8",
      "name": "Cryo",
      "country": "S"
    },
    {
      "id": "3917863ed1d89e20870b84085b496dcf",
      "name": "Centhron",
      "country": "D",
      "genre": "Band",
      "description": "Musical band"
    },
    {
      "id": "4254dcc83e96bacde8a5766fe39bd9c8",
      "name": "Intent:Outtake",
      "country": "D"
    },
    {
      "id": "98efcd93823c97c821944dd688824532",
      "name": "Grendel",
      "country": "NL",
      "genre": "Industrial",
      "description": "Musical group"
    },
    {
      "id": "44afa63336e9bd9084203dde8d0e5885",
      "name": "Sweet Ermengarde",
      "country": "D"
    },
    {
      "id": "9dbb078f25499bc09b37bff3960edfc7",
      "name": "The Sweet Kill",
      "country": "USA"
    },
    {
      "id": "216bda76efae5a26d3fe46b08f288c17",
      "name": "The Nosferatu",
      "country": "UK"
    },
    {
      "id": "b632b28e8793a74f7bf9843a22fcc71d",
      "name": "And Also The Trees",
      "country": "UK",
      "genre": "Rock",
      "description": "Rock band"
    },
    {
      "id": "f4582ea6b69a2c42f8927db535631301",
      "name": "Zeraphine",
      "country": "D",
      "genre": "Rock",
      "description": "Rock band"
    },
    {
      "id": "68834fdcdff2a84a2844bd794aa9bcdf",
      "name": "Mars",
      "country": "D",
      "genre": "Singer-Songwriter",
      "description": "American singer-songwriter and musician"
    },
    {
      "id": "4f5b2d217998fcbe135f664591d83c25",
      "name": "Crooked Mouth",
      "country": "LT",
      "description": "Musical group"
    },
    {
      "id": "519cf9e3438d52571f78f01b0f3529d0",
      "name": "In Gowan Ring",
      "country": "USA",
      "genre": "Band",
      "description": "Musical band"
    },
    {
      "id": "c0d216fda086ca4b9cf002039c625b3d",
      "name": "Death In Rome",
      "country": "AQ"
    },
    {
      "id": "73cfe151905807dcc1fc76d1c84601e7",
      "name": "Ianva",
      "country": "I",
      "genre": "Band",
      "description": "Musical band"
    },
    {
      "id": "b14bdd2dcfb3711634da80b079ef9168",
      "name": "Nachtwindheim",
      "description": "Musical group"
    },
    {
      "id": "c63728ab1da64d43804195dc96a86037",
      "name": "Kinder-Gaukeley"
    },
    {
      "id": "b25a5bcb86cc022de45ceda74d518782",
      "name": "Donner-Trummel"
    },
    {
      "id": "ed482c72dc88d7297d3ce61f7a2d3742",
      "name": "Kinder-Gaukley"
    },
    {
      "id": "5c4eb1ff35b815c9cde6cd2110dca1db",
      "name": "Ignis Draconis - Feuer-Gaukeley"
    },
    {
      "id": "403fd432400db9ae70a909058f0b47da",
      "name": "Absurd Minds",
      "country": "D",
      "genre": "Electronic",
      "description": "Musical group"
    },
    {
      "id": "b51699d453f963ae42af5b37563e3ab2",
      "name": "Spetsnaz",
      "country": "S",
      "genre": "EBM",
      "description": "Duo"
    },
    {
      "id": "aed81151bd80f98f71379581183fdf5f",
      "name": "S.I.T.D.",
      "country": "D"
    },
    {
      "id": "3e3d18638faab15973c1fae6b4841b3c",
      "name": "Funker Vogt",
      "country": "D",
      "genre": "Industrial",
      "description": "Musical band"
    },
    {
      "id": "5c838ad2cc7d6a122ec6c0644a48c0b4",
      "name": "Pouppee Fabrikk",
      "country": "S"
    },
    {
      "id": "3a7e46261a591b3e65d1e7d0b2439b20",
      "name": "Combichrist",
      "country": "USA/N",
      "genre": "Industrial",
      "description": "Band"
    },
    {
      "id": "7023ee05bfb61ec10f93e7a6d25a3ddd",
      "name": "Rabengott",
      "country": "D"
    },
    {
      "id": "63848c14b9b0a3c6a36558a81f23e26f",
      "name": "In Mitra Medusa Inri",
      "country": "D",
      "genre": "Gothic",
      "description": "Band"
    },
    {
      "id": "9e49f792ce058f3b22b8671429266daa",
      "name": "Schneewittchen Im November",
      "country": "D"
    },
    {
      "id": "be5713e3c3ff9b7643f857135f5b0d8c",
      "name": "Whispers In The Shadow",
      "country": "A",
      "genre": "Gothic",
      "description": "Rock band"
    },
    {
      "id": "df256845c7212af8a6ef1a25d13ba7be",
      "name": "Janus",
      "country": "D",
      "genre": "Band",
      "description": "Musical band"
    },
    {
      "id": "3b960988ad5d3db50fb9de3da640f998",
      "name": "QEK Junior",
      "country": "D",
      "description": "Musical group"
    },
    {
      "id": "96301feb5097dbc5b165b2b09d1cdeab",
      "name": "Linear Movement",
      "country": "B"
    },
    {
      "id": "a5002975613f1711b1e91f046d314f09",
      "name": "Sixth June",
      "country": "D/SRB"
    },
    {
      "id": "8b6d6006ec50bab3ab16f803204aa540",
      "name": "Void Vision",
      "country": "USA"
    },
    {
      "id": "231c1e12de2d2753790ade9ba85f957a",
      "name": "Turquoise Days",
      "country": "UK"
    },
    {
      "id": "9f8ada7f5d9b23f6ee43055645584275",
      "name": "Vielle- Brunnenbühne"
    },
    {
      "id": "a71125a3c3914efa5ebb9b48ec7e8875",
      "name": "Totentanz Strumpfsockig",
      "country": "D",
      "description": "Musical group"
    },
    {
      "id": "e0e52ea2de3d8cbadd16f357c46378cc",
      "name": "Arthuan Rebis",
      "country": "I",
      "genre": "Artist",
      "description": "Musical artist"
    },
    {
      "id": "0c60e0e953f8017c0888d91b25faca43",
      "name": "Vroudenspil",
      "country": "D",
      "genre": "Band",
      "description": "Musical band"
    },
    {
      "id": "6602e038e68723e86aec013cf835a235",
      "name": "Kupfergold",
      "country": "D"
    },
    {
      "id": "cd1c06e4da41121b7362540fbe8cd62c",
      "name": "Stahlmann",
      "country": "D"
    },
    {
      "id": "23ff1c42312ad5b8bc6e43808e3c66b7",
      "name": "Osi & The Jupiter",
      "country": "USA"
    },
    {
      "id": "3759d99006450cddf81cfc0d1bc35e93",
      "name": "Lovataraxx",
      "country": "F"
    },
    {
      "id": "b371a90a02b3b59ad67102d416201ea6",
      "name": "Diavol Strain",
      "country": "RCH"
    },
    {
      "id": "573d1b1ab7ba8e60118e4a3331e4e6a1",
      "name": "Balduvian Bears",
      "country": "USA",
      "genre": "Artist",
      "description": "Musical artist"
    },
    {
      "id": "3d437671f4b2808ac39679246d25dda3",
      "name": "Night In Athens",
      "country": "UK"
    },
    {
      "id": "d351305da15101130ba38d253fe3d1c1",
      "name": "Ann My Guard",
      "country": "NL"
    },
    {
      "id": "4272f0f2e28856b74a4a6774d55a8758",
      "name": "Ashram",
      "country": "I"
    },
    {
      "id": "7386bc0fc4b9453a37ebe39b6883b219",
      "name": "Kiss The Anus Of A Black Cat",
      "country": "B",
      "genre": "Band",
      "description": "Musical band"
    },
    {
      "id": "a3a7c1b0c87edd3357abc7cbab368b88",
      "name": "Anke Hachfeld [Mila Mar]",
      "country": "D",
      "genre": "Band",
      "description": "Musical band"
    },
    {
      "id": "096f9d5d65e2ffd0fcfd7a9b6b1494d8",
      "name": "Giant Crow",
      "country": "D"
    },
    {
      "id": "f849c957f2c50579eb4d85c468427be5",
      "name": "Tristwch Y Fenywod",
      "country": "UK",
      "genre": "Band",
      "description": "Musical band"
    },
    {
      "id": "f62a95c25171543afbf8de2764df5a1d",
      "name": "Faetooth",
      "country": "USA"
    },
    {
      "id": "fc31f5e2ceb6a2ee9ec213761aa00caf",
      "name": "Blazing Eternity",
      "country": "DK"
    },
    {
      "id": "0c12da5fb58bfc10d8f6d2e6f28f50fd",
      "name": "Resplandor",
      "country": "PE/NL"
    },
    {
      "id": "922a7010bd95e72ec7635c5942c4a449",
      "name": "Midas Fall",
      "country": "UK"
    },
    {
      "id": "03168ab0bd5ed4c8125c88ab3b02a8f2",
      "name": "In The Woods",
      "country": "N",
      "genre": "Black Metal",
      "description": "Band"
    },
    {
      "id": "a3e6115fc85d91de3878bacfd80dbea0",
      "name": "Christ Vs Warhol",
      "country": "USA"
    },
    {
      "id": "d78bcaac146002037edd94626a00d060",
      "name": "Shrouds",
      "country": "USA"
    },
    {
      "id": "b57859ba1abaebac6ad9e3121c84a708",
      "name": "Lucas Lanthier`s Cinema Strange",
      "country": "USA"
    },
    {
      "id": "512a1e4bde5d9c3949612672fb95891a",
      "name": "Eva O.",
      "country": "USA"
    },
    {
      "id": "c15d401e7380b4ac09db839cc369da93",
      "name": "Fangs On Fur",
      "country": "USA"
    },
    {
      "id": "531ac363659e2b48c5794282bb6b32b4",
      "name": "Veljanov",
      "country": "D"
    },
    {
      "id": "b549689b6e61e488dc4087527f392beb",
      "name": "Ventus Infecto"
    },
    {
      "id": "41dff6cb80483b0c4408f47b9aa32875",
      "name": "Crimson Veil",
      "country": "UK",
      "genre": "Band",
      "description": "Musical band"
    },
    {
      "id": "eb62af7492157c676fb8fc9692e83447",
      "name": "Xandria",
      "country": "D",
      "genre": "Symphonic Metal",
      "description": "Band"
    },
    {
      "id": "534982fddde518d146945176d145cd12",
      "name": "Drab Majesty",
      "country": "USA",
      "genre": "Band",
      "description": "Musical band"
    },
    {
      "id": "143af26de9d57bf624771616318aaf7c",
      "name": "Witt",
      "country": "D"
    },
    {
      "id": "50ab5192d58b8dc6fd76129ebc416238",
      "name": "Silke Bischoff",
      "country": "D"
    },
    {
      "id": "1da6407d4b67c0196e5076d3817ad491",
      "name": "Public Image Limited",
      "country": "UK"
    },
    {
      "id": "dbd9414e22c006289473493a6d1389f8",
      "name": "Lakeside-X",
      "country": "CZ"
    },
    {
      "id": "af2cd7cf14f5b9165b0b074aea349a21",
      "name": "Beborn Beton",
      "country": "D",
      "genre": "Synthpop",
      "description": "Band"
    },
    {
      "id": "747677bc2da67e70ff5c1a900b35fbab",
      "name": "Morphose",
      "country": "D"
    },
    {
      "id": "f6237bec3009c68bfe45b6553f354fed",
      "name": "Anything Box",
      "country": "USA"
    },
    {
      "id": "1bbdbbc1be9859edf9ae00fa9f2da113",
      "name": "Icon Of Coil",
      "country": "N",
      "genre": "Electronic",
      "description": "Musical band"
    },
    {
      "id": "ba628e6419eeafc36eda4cb2ca6e3492",
      "name": "Kalt",
      "country": "F"
    },
    {
      "id": "3af2ee7fa80839fdd552e3f55c244ac7",
      "name": "Sturm Cafe",
      "country": "S"
    },
    {
      "id": "57e949565f9d4fc031ecac41915b25ef",
      "name": "Container 90",
      "country": "S"
    },
    {
      "id": "d37dc1d462431c21ab36855d98590bf2",
      "name": "The Invincible Spirit",
      "country": "D",
      "genre": "Band",
      "description": "Musical band"
    },
    {
      "id": "5d98c40222b27767c2639dd5d4f2cbbd",
      "name": "Calva Y Nada",
      "country": "D"
    },
    {
      "id": "572fad4f58b156b713e8e6ff4c58cc5b",
      "name": "Ingrimm",
      "country": "D"
    },
    {
      "id": "93ddc62e1b13b6ffbaf5faacf4a45a28",
      "name": "Nachtwindheim- Brunnenbühne"
    },
    {
      "id": "48e2ca1c28ae9e7dadcda6ad935da2ed",
      "name": "Alvader",
      "country": "NL"
    },
    {
      "id": "d69462bef6601bb8d6e3ffda067399d9",
      "name": "Gernotshagen",
      "country": "D",
      "genre": "Band",
      "description": "Musical band"
    },
    {
      "id": "f3d7662a9107de0635f647b83ae55566",
      "name": "Finntroll",
      "country": "FIN",
      "genre": "Black Metal",
      "description": "Band"
    },
    {
      "id": "f10f1ea9e6a334fe99c69ad0102908f9",
      "name": "Fakir-Gaukeley- Brunnenbühne"
    },
    {
      "id": "f65d3d938f139227d9f22ad3d3a473df",
      "name": "Kalandra",
      "country": "N/S",
      "genre": "Musician",
      "description": "Czech musician"
    },
    {
      "id": "281a836af1e09e8b25fdd84c5a882954",
      "name": "André Alabaster & The Curved Beaks",
      "country": "D"
    },
    {
      "id": "833a28074b156b57b538cc1332589c7b",
      "name": "Hallowed Hearts",
      "country": "USA"
    },
    {
      "id": "733c98ccb843041211b866fe9a699faf",
      "name": "Sad Madona",
      "country": "F"
    },
    {
      "id": "4dda4f48c7a4b87d8295b482a567d511",
      "name": "Psyche",
      "country": "CDN"
    },
    {
      "id": "4a0b3fae795fdebddaa303ad85096ebd",
      "name": "Lone Assembly",
      "country": "CH"
    },
    {
      "id": "02e2007a30a2439074c584e125328e23",
      "name": "Soror Dolorosa",
      "country": "F",
      "genre": "Band",
      "description": "Musical band"
    },
    {
      "id": "1d4042750dd8d231fdc0d39ce58f664c",
      "name": "Escape With Romeo",
      "country": "D"
    },
    {
      "id": "8fbb28f1334219a3ac918273f7690c4e",
      "name": "Phil Shoenfelt & Southern Cross",
      "country": "UK/CZ",
      "genre": "Musician",
      "description": "English musician and author"
    },
    {
      "id": "a277e254800234eeb726a345de2b4e5f",
      "name": "Saigon Blue Rain",
      "country": "F",
      "genre": "Band",
      "description": "Musical band"
    },
    {
      "id": "9945003528c4ef2ca61e3cea99bb2250",
      "name": "Vkgoeswild",
      "country": "UA"
    },
    {
      "id": "ae860b11ae80b4642e8a9fb24050b490",
      "name": "Skemer",
      "country": "B"
    },
    {
      "id": "92a2a0896f3ef8ba4ce2368a23836f10",
      "name": "Jakuzi",
      "country": "TR",
      "genre": "Synthpop",
      "description": "Band"
    },
    {
      "id": "88a9444a8827772b59b4ca7f61cb88e6",
      "name": "Patriarchy",
      "country": "USA"
    },
    {
      "id": "1ef78d40643f4e530d8742462c69449e",
      "name": "Light Asylum",
      "country": "USA",
      "genre": "Darkwave",
      "description": "Musical band"
    },
    {
      "id": "23bcc024a0a6c53546d6fdd25b1673ee",
      "name": "Linea Aspera",
      "country": "AUS/UK",
      "genre": "Electronic",
      "description": "Electronic duo"
    },
    {
      "id": "023699fca54ef93f1d3be05bb9a9fa7d",
      "name": "Noisex",
      "country": "D"
    },
    {
      "id": "080e22165203b5c3d7d8d46c6268e98a",
      "name": "Xotox",
      "country": "D"
    },
    {
      "id": "b35ef33f378d58502ae84288d791a463",
      "name": "Liebknecht",
      "country": "D"
    },
    {
      "id": "9dc73fe924bb17caae376ec76afa5d0d",
      "name": "Rhys Fulber",
      "country": "CDN",
      "genre": "Electronic",
      "description": "Canadian musician"
    },
    {
      "id": "db5c9ed3e471212d45cdd6c321066d60",
      "name": "Klangstabil",
      "country": "D"
    },
    {
      "id": "d32f061033ed3864c079c82ee2e6e045",
      "name": "Bleib Modern",
      "country": "D"
    },
    {
      "id": "97036da18452da08c0bbd821411df1bf",
      "name": "Deceits",
      "country": "USA"
    },
    {
      "id": "7054b6f3ca314c758037dfda2432d39e",
      "name": "Silent Runners",
      "country": "NL"
    },
    {
      "id": "33981a59ed065b4fa9fe1b0e24230949",
      "name": "Plastique Noir",
      "country": "BR"
    },
    {
      "id": "216f70178e7f3577a557612c606b5993",
      "name": "Darkways",
      "country": "E",
      "genre": "Band",
      "description": "Musical band"
    },
    {
      "id": "f2ea9a7dfdcaaac59523b2babe7d018e",
      "name": "French Police",
      "country": "USA"
    },
    {
      "id": "b0ab75d3f09f8edf3579ea58aae3571b",
      "name": "This Cold Night",
      "country": "USA",
      "genre": "Band",
      "description": "Musical band"
    },
    {
      "id": "26d62c17c1bda3adecc4c5b136ac0318",
      "name": "Ventus Invecto"
    },
    {
      "id": "62b1a15d39a5fc95e1fa28b2af2f10ba",
      "name": "Fakir-Gaukeley"
    },
    {
      "id": "ccdc1d2d7618e67e0c2b08b4ff9fd8f0",
      "name": "Ost+Front",
      "country": "D"
    },
    {
      "id": "63bd91393913705437d42a3a7bf4535b",
      "name": "L`Ame Immortelle",
      "country": "A"
    },
    {
      "id": "8227ff91b5086c88e66f991aa6f0371b",
      "name": "The 69 Eyes",
      "country": "FIN",
      "genre": "Rock",
      "description": "Rock band"
    },
    {
      "id": "98f5c5baf32215e003244fcf2cace66a",
      "name": "Camouflage",
      "country": "D",
      "genre": "Synthpop",
      "description": "Pop trio"
    },
    {
      "id": "191cfb6f9caecb6571a1782954e8205e",
      "name": "New Model Army",
      "country": "UK",
      "genre": "Rock",
      "description": "Rock band"
    },
    {
      "id": "510ddd5524ab16d583d8b7317a55f474",
      "name": "Protokoll 19",
      "country": "USA"
    },
    {
      "id": "1a1a2554ec1a79500fb68b972ba44ed6",
      "name": "Torul",
      "country": "SLO",
      "genre": "Band",
      "description": "Musical band"
    },
    {
      "id": "f0520a57e6e312d5917bfd2a3a943b35",
      "name": "Vomito Negro",
      "country": "B",
      "genre": "Electronic",
      "description": "Band"
    },
    {
      "id": "71c982b9a58f293b1b3778705e67574b",
      "name": "Chrom",
      "country": "D"
    },
    {
      "id": "e82f40d2f4df9dd006ff8557e0f85691",
      "name": "Orange Sector",
      "country": "D",
      "genre": "EBM",
      "description": "Band"
    },
    {
      "id": "2e8850d6645fff92c503e26b88ab61c3",
      "name": "A Cloud Of Ravens",
      "country": "USA",
      "genre": "Rock",
      "description": "Rock duo"
    },
    {
      "id": "87ba7b5c0de45056bb36cd27d80b072c",
      "name": "Future Nobodies",
      "country": "USA"
    },
    {
      "id": "1e7c41955052e131a4f4e6d82161dc01",
      "name": "The Exploding Boy",
      "country": "S"
    },
    {
      "id": "bab198e4a30f6eeb50756bfbb0579227",
      "name": "The Membranes",
      "country": "UK",
      "genre": "Post-Punk",
      "description": "Band"
    },
    {
      "id": "54331b9b16e65e2658e391486720d69f",
      "name": "Delva",
      "country": "D"
    },
    {
      "id": "bc77f9a10f311a432c65bdd4c56eca7f",
      "name": "Vermaledeyt",
      "country": "D"
    },
    {
      "id": "8403aed2db8164a17046f4d61a8e8e77",
      "name": "Haggefugg",
      "country": "D"
    },
    {
      "id": "de26f58f2892752a1c10cadcee7388ec",
      "name": "Ventus Infecto - Brunnenbühne"
    },
    {
      "id": "259e1392c7248aa73739b0d44ed805a9",
      "name": "Letzte Instanz",
      "country": "D",
      "genre": "Punk",
      "description": "Rock band"
    },
    {
      "id": "ac47baa2169b8473568fe45652c24bf8",
      "name": "Deus Ex Lumina",
      "country": "ARG/D",
      "genre": "Artist",
      "description": "Musical artist"
    },
    {
      "id": "8ad41aa0f71854f2aee6b67300ccd420",
      "name": "Henric De La Cour",
      "country": "S"
    },
    {
      "id": "cc87aa9f484bf88cd9db2f9c8deb8916",
      "name": "Black Nail Cabaret",
      "country": "H",
      "description": "Musical duo"
    },
    {
      "id": "3d09ea3d53516ab906a53ae0bb938943",
      "name": "Stahlnetz",
      "country": "D"
    },
    {
      "id": "39841b789f8c4837496688100c4c3efd",
      "name": "Lucifer Star Machine",
      "country": "D"
    },
    {
      "id": "d95995a43e371aec2c7f4df40f7fdc42",
      "name": "Dark Ride",
      "country": "USA"
    },
    {
      "id": "065266d69f062ec2f65000fbc443babb",
      "name": "Zombina And The Skeletones",
      "country": "UK",
      "genre": "Punk",
      "description": "Rock band"
    },
    {
      "id": "2369803b80bf00925dbfdae202d393e7",
      "name": "Long Tall Texans",
      "country": "UK"
    },
    {
      "id": "ffc59bd768d00cc390ee33007833eb81",
      "name": "Nim Vind",
      "country": "CDN",
      "genre": "Punk",
      "description": "Musical band"
    },
    {
      "id": "ff332e46405212a70a15eb2e5b4037b4",
      "name": "Mode In Gliany",
      "country": "BZH"
    },
    {
      "id": "293f2bd2a800eb08f306b43506383b4d",
      "name": "Sturle Dagsland",
      "country": "N"
    },
    {
      "id": "1c72dac6197c1660c719c4ecad7d74f0",
      "name": "Cut Hands",
      "country": "UK"
    },
    {
      "id": "b411aa827c064877860f16c3cdc3d1b9",
      "name": "Mona Mur & En Esch",
      "country": "D"
    },
    {
      "id": "1d518b7c2e383a766be63bf35fb3152d",
      "name": "Shortparis",
      "country": "RUS",
      "genre": "Experimental",
      "description": "Musical band"
    },
    {
      "id": "ab95492f5a66c1557125e384f2cee6bd",
      "name": "Vielle"
    },
    {
      "id": "6cc0c9b8482b9d099c84caa8c72ffc40",
      "name": "Umzug aller Vaganten"
    }
  ],
  "locations": [
    {
      "id": "59c80748f493ceecd0d76b57ebe2de2e",
      "name": "agra",
      "city": "Leipzig"
    },
    {
      "id": "25943ede1bfc2531bd6a8814bbb6fd57",
      "name": "Felsenkeller",
      "city": "Leipzig"
    },
    {
      "id": "ce206d740f859a7a2e691c7e8a2c1888",
      "name": "Haus Leipzig",
      "city": "Leipzig"
    },
    {
      "id": "a4fa7bae7434338c5143943b5e48efb4",
      "name": "Heidnisches Dorf / Torhaus Dölitz",
      "city": "Leipzig"
    },
    {
      "id": "4eb8b676e4c650a0f196b4ee47ae913d",
      "name": "Moritzbastei",
      "city": "Leipzig"
    },
    {
      "id": "16bdce7af743ea1b04aef7d4dcefecd0",
      "name": "Parkschloß - Ballsaal",
      "city": "Leipzig"
    },
    {
      "id": "9c3e9e09a83273d69f49c4c39006941c",
      "name": "Stadtbad",
      "city": "Leipzig"
    },
    {
      "id": "a4df6f5c5655dd443bdaa2ac28ec6105",
      "name": "Täubchenthal",
      "city": "Leipzig"
    },
    {
      "id": "2a55f3eca82c7bfb32506bcf7d3c1561",
      "name": "Volkspalast Kantine",
      "city": "Leipzig"
    },
    {
      "id": "f9de432063e814bcb67ea92bf3713fdb",
      "name": "Volkspalast Kuppelhalle",
      "city": "Leipzig"
    },
    {
      "id": "5fe101bcd2edae028474473e52b9751f",
      "name": "Mittelaltermarkt - Moritzbastei",
      "city": "Leipzig"
    },
    {
      "id": "ddc89946f8e5b850cd1a5742406c6c87",
      "name": "Parkschloß - Barocksaal",
      "city": "Leipzig"
    },
    {
      "id": "ee531432311a801a59d6a2cef8c1f6fc",
      "name": "Peterskirche",
      "city": "Leipzig"
    }
  ],
  "events": [
    {
      "id": "2fbda9c69749ef078ac0b8680157d6b1",
      "bandId": "1bb16e9cb667084ce5a86f766d19d6f8",
      "locationId": "59c80748f493ceecd0d76b57ebe2de2e",
      "date": "2025-06-06",
      "startTime": "18:00",
      "category": "band"
    },
    {
      "id": "223cb423bf40e593da6202dcb03fea41",
      "bandId": "e8aa179ac2877d19f2fb242445036f84",
      "locationId": "59c80748f493ceecd0d76b57ebe2de2e",
      "date": "2025-06-06",
      "startTime": "19:15",
      "category": "band"
    },
    {
      "id": "e54d5ea26e878fe761418cdbf661879e",
      "bandId": "e29debecede17e5c0e7f030e0cc2f9a1",
      "locationId": "59c80748f493ceecd0d76b57ebe2de2e",
      "date": "2025-06-06",
      "startTime": "20:45",
      "category": "band"
    },
    {
      "id": "7ff71980769a8bdcd59e6287fa7c7c6e",
      "bandId": "d5a5ca83f36b3bb6d201d4b1974b0b1a",
      "locationId": "59c80748f493ceecd0d76b57ebe2de2e",
      "date": "2025-06-06",
      "startTime": "22:10",
      "category": "band"
    },
    {
      "id": "4b40166d17128b3f4d36fe7685ca6874",
      "bandId": "4781ac9273d3335229ca90e8e00a1c71",
      "locationId": "59c80748f493ceecd0d76b57ebe2de2e",
      "date": "2025-06-07",
      "startTime": "00:00",
      "category": "band"
    },
    {
      "id": "5a1dd2d7e8ea7e0a19289039df77a6f7",
      "bandId": "f470592b0d38e198b70915bb4a05156b",
      "locationId": "25943ede1bfc2531bd6a8814bbb6fd57",
      "date": "2025-06-06",
      "startTime": "17:00",
      "category": "band"
    },
    {
      "id": "8d47cb07cc3ca74e9190eb5983e95a43",
      "bandId": "f74ee7f89540fcc53f4b12b82cc42025",
      "locationId": "25943ede1bfc2531bd6a8814bbb6fd57",
      "date": "2025-06-06",
      "startTime": "18:10",
      "category": "band"
    },
    {
      "id": "49c95d83af466f0626865a3fea20d86a",
      "bandId": "90928c6e169c17889b85fbe546457cf2",
      "locationId": "25943ede1bfc2531bd6a8814bbb6fd57",
      "date": "2025-06-06",
      "startTime": "19:30",
      "category": "band"
    },
    {
      "id": "8a7cb16b5f529b4e2e7139d82bd5ed7b",
      "bandId": "84b0318f8f015ba67aff86c211d2fcd8",
      "locationId": "25943ede1bfc2531bd6a8814bbb6fd57",
      "date": "2025-06-06",
      "startTime": "21:00",
      "category": "band"
    },
    {
      "id": "58b74c89a80e6cafa948e8c7d5ea096f",
      "bandId": "689e88226f2d0027b679be5b3f1e421e",
      "locationId": "25943ede1bfc2531bd6a8814bbb6fd57",
      "date": "2025-06-06",
      "startTime": "22:30",
      "category": "band"
    },
    {
      "id": "73143956f35cbb862cb4209b4ffdd1d7",
      "bandId": "273c0de9551279a38a2ca50cb65c467c",
      "locationId": "ce206d740f859a7a2e691c7e8a2c1888",
      "date": "2025-06-06",
      "startTime": "17:00",
      "category": "band"
    },
    {
      "id": "efaee2a20b5c7811cbeefa1393b230a8",
      "bandId": "bd7fbdd6d4b03e6bce080d78fc575a22",
      "locationId": "ce206d740f859a7a2e691c7e8a2c1888",
      "date": "2025-06-06",
      "startTime": "18:20",
      "category": "band"
    },
    {
      "id": "679fd19d65f3c9012c2565b7cf8c0094",
      "bandId": "c126b3dbd774d72af2d51cdc0e832a07",
      "locationId": "ce206d740f859a7a2e691c7e8a2c1888",
      "date": "2025-06-06",
      "startTime": "19:40",
      "category": "band"
    },
    {
      "id": "a0435ed149aaeb1f15dc1990afb0d916",
      "bandId": "efee29522a06e60ec0a3e9c1e71f6ece",
      "locationId": "ce206d740f859a7a2e691c7e8a2c1888",
      "date": "2025-06-06",
      "startTime": "21:00",
      "category": "band"
    },
    {
      "id": "3be0c523cf175bf354a1eea5fc51c9a6",
      "bandId": "95f4ca3978931050c272981bd9116562",
      "locationId": "ce206d740f859a7a2e691c7e8a2c1888",
      "date": "2025-06-06",
      "startTime": "22:30",
      "category": "band"
    },
    {
      "id": "1608fdeaee6aa9d3ec2e70728852a05a",
      "bandId": "b64884a0464d33488a31b8d3379eb3ff",
      "locationId": "a4fa7bae7434338c5143943b5e48efb4",
      "date": "2025-06-06",
      "startTime": "12:00",
      "category": "show"
    },
    {
      "id": "3a6f33c627f24f9cc4f80be679fc130e",
      "bandId": "c4782c02d2b8f5cff0fb06a1f253322a",
      "locationId": "a4fa7bae7434338c5143943b5e48efb4",
      "date": "2025-06-06",
      "startTime": "13:00",
      "category": "show"
    },
    {
      "id": "024bc29b91bdd8740df63d5315f47732",
      "bandId": "b64884a0464d33488a31b8d3379eb3ff",
      "locationId": "a4fa7bae7434338c5143943b5e48efb4",
      "date": "2025-06-06",
      "startTime": "13:45",
      "category": "show"
    },
    {
      "id": "0b9e4486243308cb2686bca28b1dfd8d",
      "bandId": "79dbf50acd5819a5d7102cb9100d3cbe",
      "locationId": "a4fa7bae7434338c5143943b5e48efb4",
      "date": "2025-06-06",
      "startTime": "14:00",
      "category": "band"
    },
    {
      "id": "3086200f26eb131cc57523ecdcfab5f0",
      "bandId": "09a9318508da52652852638eacbf39b4",
      "locationId": "a4fa7bae7434338c5143943b5e48efb4",
      "date": "2025-06-06",
      "startTime": "15:00",
      "category": "show"
    },
    {
      "id": "61ec5291d989dca6f5b091a0c31c823c",
      "bandId": "4fe2356b10918b2cc29ba0ef7463a484",
      "locationId": "a4fa7bae7434338c5143943b5e48efb4",
      "date": "2025-06-06",
      "startTime": "15:30",
      "category": "band"
    },
    {
      "id": "dcfafdeedb6688e2f795630d12641fa2",
      "bandId": "0f3adc8652c99ef33b3f945e29a0ac60",
      "locationId": "a4fa7bae7434338c5143943b5e48efb4",
      "date": "2025-06-06",
      "startTime": "16:30",
      "category": "show"
    },
    {
      "id": "f29577d7067d77369c8ead66bbc7f7ae",
      "bandId": "13d38c86b45c92bc250fbfb96f0ccc89",
      "locationId": "a4fa7bae7434338c5143943b5e48efb4",
      "date": "2025-06-06",
      "startTime": "17:00",
      "category": "band"
    },
    {
      "id": "55add8a0cc6ff55121ca4547e31723c6",
      "bandId": "b64884a0464d33488a31b8d3379eb3ff",
      "locationId": "a4fa7bae7434338c5143943b5e48efb4",
      "date": "2025-06-06",
      "startTime": "17:00",
      "category": "show"
    },
    {
      "id": "973cb5b3ded6502051f1b1088e5b5600",
      "bandId": "c75d4ba31f3b96b5a6647cb58620d4a1",
      "locationId": "a4fa7bae7434338c5143943b5e48efb4",
      "date": "2025-06-06",
      "startTime": "18:00",
      "category": "show"
    },
    {
      "id": "26b733db38e31671456ee65ac9ecaefc",
      "bandId": "6ea6abfda82464e53a03a0c8a5c354ed",
      "locationId": "a4fa7bae7434338c5143943b5e48efb4",
      "date": "2025-06-06",
      "startTime": "18:40",
      "category": "band"
    },
    {
      "id": "cbb7b04874175525a5b5fd4f778e4197",
      "bandId": "c989e5e42db682b1a5d0fc1cdf630bf4",
      "locationId": "a4fa7bae7434338c5143943b5e48efb4",
      "date": "2025-06-06",
      "startTime": "19:00",
      "category": "show"
    },
    {
      "id": "1fd56d5edb2d24d7b2c25c4d38a50031",
      "bandId": "47a087cd05cd1ae463d66265384c4fa8",
      "locationId": "a4fa7bae7434338c5143943b5e48efb4",
      "date": "2025-06-06",
      "startTime": "20:00",
      "category": "show"
    },
    {
      "id": "4f25528f91b07d6657778dc577ea8ef9",
      "bandId": "97d64296e472cacc626e54fbc933e665",
      "locationId": "a4fa7bae7434338c5143943b5e48efb4",
      "date": "2025-06-06",
      "startTime": "20:35",
      "category": "band"
    },
    {
      "id": "260296004cc69db80f4632afb0c28ffc",
      "bandId": "b64884a0464d33488a31b8d3379eb3ff",
      "locationId": "a4fa7bae7434338c5143943b5e48efb4",
      "date": "2025-06-06",
      "startTime": "21:00",
      "category": "show"
    },
    {
      "id": "028ea262cb17339b5d0d13361eb3121d",
      "bandId": "47a9cfcd95a53206e25acb64767e205f",
      "locationId": "a4fa7bae7434338c5143943b5e48efb4",
      "date": "2025-06-06",
      "startTime": "22:35",
      "category": "show"
    },
    {
      "id": "214229e8e6fec8ec2c17dd52a21db888",
      "bandId": "cbc4fcab7a696e9e8eca061ce20f70bd",
      "locationId": "4eb8b676e4c650a0f196b4ee47ae913d",
      "date": "2025-06-06",
      "startTime": "20:00",
      "category": "band"
    },
    {
      "id": "18d7399562907d62f133d0a0bd7e1eff",
      "bandId": "f091dc80f3499920c4ae7b263592d06d",
      "locationId": "4eb8b676e4c650a0f196b4ee47ae913d",
      "date": "2025-06-06",
      "startTime": "21:00",
      "category": "band"
    },
    {
      "id": "1b64cb0c6a7cb6e1a4d9d44aa9f5af4b",
      "bandId": "db83bbe4cffc2097fb1b83c23926c185",
      "locationId": "4eb8b676e4c650a0f196b4ee47ae913d",
      "date": "2025-06-06",
      "startTime": "22:00",
      "category": "band"
    },
    {
      "id": "3e2434b34f0fc38f55eba7e2e5f04a63",
      "bandId": "c641e02e5ddbe82589cbebbe9bb2ed03",
      "locationId": "4eb8b676e4c650a0f196b4ee47ae913d",
      "date": "2025-06-06",
      "startTime": "23:10",
      "category": "band"
    },
    {
      "id": "ff6c5074dbb287d625a4879ac0cca1aa",
      "bandId": "4d32db1f0da7bc8aa8baa688424dee8b",
      "locationId": "16bdce7af743ea1b04aef7d4dcefecd0",
      "date": "2025-06-06",
      "startTime": "23:00",
      "category": "band"
    },
    {
      "id": "916d22f77002cba8a6fc7828e69171ec",
      "bandId": "38c91565571c7eba657528a02d57affd",
      "locationId": "9c3e9e09a83273d69f49c4c39006941c",
      "date": "2025-06-06",
      "startTime": "16:30",
      "category": "band"
    },
    {
      "id": "48028a3af7616021b552c05d4046bd54",
      "bandId": "ee20998fd5da6460ec33d4c1dac0efd8",
      "locationId": "9c3e9e09a83273d69f49c4c39006941c",
      "date": "2025-06-06",
      "startTime": "17:50",
      "category": "band"
    },
    {
      "id": "f447074038e5d2ea039116af013e7ed5",
      "bandId": "3917863ed1d89e20870b84085b496dcf",
      "locationId": "9c3e9e09a83273d69f49c4c39006941c",
      "date": "2025-06-06",
      "startTime": "19:10",
      "category": "band"
    },
    {
      "id": "d00436095816fa5d20de4ea834455a7d",
      "bandId": "4254dcc83e96bacde8a5766fe39bd9c8",
      "locationId": "9c3e9e09a83273d69f49c4c39006941c",
      "date": "2025-06-06",
      "startTime": "20:40",
      "category": "band"
    },
    {
      "id": "33858517412358d91f626f7e47119c3c",
      "bandId": "98efcd93823c97c821944dd688824532",
      "locationId": "9c3e9e09a83273d69f49c4c39006941c",
      "date": "2025-06-06",
      "startTime": "22:10",
      "category": "band"
    },
    {
      "id": "2b8a1e2ae3dea335023ca17c1bc77f96",
      "bandId": "44afa63336e9bd9084203dde8d0e5885",
      "locationId": "a4df6f5c5655dd443bdaa2ac28ec6105",
      "date": "2025-06-06",
      "startTime": "17:30",
      "category": "band"
    },
    {
      "id": "fccc5a0f7580c5e361f2724c20defd4f",
      "bandId": "9dbb078f25499bc09b37bff3960edfc7",
      "locationId": "a4df6f5c5655dd443bdaa2ac28ec6105",
      "date": "2025-06-06",
      "startTime": "18:40",
      "category": "band"
    },
    {
      "id": "6d38392d53e71b8b4a437b18ec6365f7",
      "bandId": "216bda76efae5a26d3fe46b08f288c17",
      "locationId": "a4df6f5c5655dd443bdaa2ac28ec6105",
      "date": "2025-06-06",
      "startTime": "20:00",
      "category": "band"
    },
    {
      "id": "f3b21207cdaf08255de167d6376a43aa",
      "bandId": "b632b28e8793a74f7bf9843a22fcc71d",
      "locationId": "a4df6f5c5655dd443bdaa2ac28ec6105",
      "date": "2025-06-06",
      "startTime": "21:20",
      "category": "band"
    },
    {
      "id": "3a689e82c6972b5a9db27ea7dd0d0b99",
      "bandId": "f4582ea6b69a2c42f8927db535631301",
      "locationId": "a4df6f5c5655dd443bdaa2ac28ec6105",
      "date": "2025-06-06",
      "startTime": "22:40",
      "category": "band"
    },
    {
      "id": "ff2c0b9103494302c70b376eab98530b",
      "bandId": "68834fdcdff2a84a2844bd794aa9bcdf",
      "locationId": "2a55f3eca82c7bfb32506bcf7d3c1561",
      "date": "2025-06-06",
      "startTime": "19:15",
      "category": "band"
    },
    {
      "id": "0bb557aad6b1785872aac45ebeb5c691",
      "bandId": "4f5b2d217998fcbe135f664591d83c25",
      "locationId": "2a55f3eca82c7bfb32506bcf7d3c1561",
      "date": "2025-06-06",
      "startTime": "21:45",
      "category": "band"
    },
    {
      "id": "09e4da7cde63daf7a05df91e2f250a1a",
      "bandId": "519cf9e3438d52571f78f01b0f3529d0",
      "locationId": "f9de432063e814bcb67ea92bf3713fdb",
      "date": "2025-06-06",
      "startTime": "18:00",
      "category": "band"
    },
    {
      "id": "1094f2336ad8fc5e5aa86d6852f22e5e",
      "bandId": "c0d216fda086ca4b9cf002039c625b3d",
      "locationId": "f9de432063e814bcb67ea92bf3713fdb",
      "date": "2025-06-06",
      "startTime": "20:30",
      "category": "band"
    },
    {
      "id": "f8701bcdfd872881dab534c5d88e9060",
      "bandId": "73cfe151905807dcc1fc76d1c84601e7",
      "locationId": "f9de432063e814bcb67ea92bf3713fdb",
      "date": "2025-06-06",
      "startTime": "23:00",
      "category": "band"
    },
    {
      "id": "12307bd563d621251f0123d49e50a740",
      "bandId": "b14bdd2dcfb3711634da80b079ef9168",
      "locationId": "5fe101bcd2edae028474473e52b9751f",
      "date": "2025-06-06",
      "startTime": "13:00",
      "category": "show"
    },
    {
      "id": "600e2f1420f885726541c640f80419bc",
      "bandId": "c63728ab1da64d43804195dc96a86037",
      "locationId": "5fe101bcd2edae028474473e52b9751f",
      "date": "2025-06-06",
      "startTime": "14:00",
      "category": "show"
    },
    {
      "id": "78a7f58eb06ec9aaaee2427c0512fe8d",
      "bandId": "b25a5bcb86cc022de45ceda74d518782",
      "locationId": "5fe101bcd2edae028474473e52b9751f",
      "date": "2025-06-06",
      "startTime": "15:00",
      "category": "show"
    },
    {
      "id": "68dce3d09020fcab87ce283161d11dcb",
      "bandId": "ed482c72dc88d7297d3ce61f7a2d3742",
      "locationId": "5fe101bcd2edae028474473e52b9751f",
      "date": "2025-06-06",
      "startTime": "16:00",
      "category": "show"
    },
    {
      "id": "58d34e4918150687575ea36128455320",
      "bandId": "b14bdd2dcfb3711634da80b079ef9168",
      "locationId": "5fe101bcd2edae028474473e52b9751f",
      "date": "2025-06-06",
      "startTime": "17:00",
      "category": "show"
    },
    {
      "id": "ff291129f57ad9ad0478d746535d7aff",
      "bandId": "b25a5bcb86cc022de45ceda74d518782",
      "locationId": "5fe101bcd2edae028474473e52b9751f",
      "date": "2025-06-06",
      "startTime": "18:00",
      "category": "show"
    },
    {
      "id": "cb4405fb7a91514bb78f9a5b36fc8fc0",
      "bandId": "b14bdd2dcfb3711634da80b079ef9168",
      "locationId": "5fe101bcd2edae028474473e52b9751f",
      "date": "2025-06-06",
      "startTime": "19:00",
      "category": "show"
    },
    {
      "id": "869d8f6740f6b69f34198fdc1ce5bd84",
      "bandId": "b25a5bcb86cc022de45ceda74d518782",
      "locationId": "5fe101bcd2edae028474473e52b9751f",
      "date": "2025-06-06",
      "startTime": "20:00",
      "category": "show"
    },
    {
      "id": "0f6b3ab40304b3728cbc08b70fd90b24",
      "bandId": "5c4eb1ff35b815c9cde6cd2110dca1db",
      "locationId": "5fe101bcd2edae028474473e52b9751f",
      "date": "2025-06-06",
      "startTime": "21:30",
      "category": "show"
    },
    {
      "id": "4927060288582af3dbaa111fc76a1f5d",
      "bandId": "403fd432400db9ae70a909058f0b47da",
      "locationId": "59c80748f493ceecd0d76b57ebe2de2e",
      "date": "2025-06-07",
      "startTime": "16:00",
      "category": "band"
    },
    {
      "id": "c589e9992865a71ddfc8c352883b658b",
      "bandId": "b51699d453f963ae42af5b37563e3ab2",
      "locationId": "59c80748f493ceecd0d76b57ebe2de2e",
      "date": "2025-06-07",
      "startTime": "17:15",
      "category": "band"
    },
    {
      "id": "85f963fe371148bcea0663b5b6368df1",
      "bandId": "aed81151bd80f98f71379581183fdf5f",
      "locationId": "59c80748f493ceecd0d76b57ebe2de2e",
      "date": "2025-06-07",
      "startTime": "18:45",
      "category": "band"
    },
    {
      "id": "b953f24578fd542dec8727b53f2eeb6b",
      "bandId": "3e3d18638faab15973c1fae6b4841b3c",
      "locationId": "59c80748f493ceecd0d76b57ebe2de2e",
      "date": "2025-06-07",
      "startTime": "20:10",
      "category": "band"
    },
    {
      "id": "7195d3458018271a301be0b02dc0f2ee",
      "bandId": "5c838ad2cc7d6a122ec6c0644a48c0b4",
      "locationId": "59c80748f493ceecd0d76b57ebe2de2e",
      "date": "2025-06-07",
      "startTime": "21:50",
      "category": "band"
    },
    {
      "id": "cebea07bd57ae3ef4a5799bec181a51d",
      "bandId": "3a7e46261a591b3e65d1e7d0b2439b20",
      "locationId": "59c80748f493ceecd0d76b57ebe2de2e",
      "date": "2025-06-07",
      "startTime": "23:30",
      "category": "band"
    },
    {
      "id": "9d2106d8885f51f1863a0566e9216aff",
      "bandId": "7023ee05bfb61ec10f93e7a6d25a3ddd",
      "locationId": "25943ede1bfc2531bd6a8814bbb6fd57",
      "date": "2025-06-07",
      "startTime": "16:30",
      "category": "band"
    },
    {
      "id": "e7e81d0c182dd0f91d6c016fbfe18f92",
      "bandId": "63848c14b9b0a3c6a36558a81f23e26f",
      "locationId": "25943ede1bfc2531bd6a8814bbb6fd57",
      "date": "2025-06-07",
      "startTime": "17:50",
      "category": "band"
    },
    {
      "id": "a2a8759e01a43f78aaa013859e11273e",
      "bandId": "9e49f792ce058f3b22b8671429266daa",
      "locationId": "25943ede1bfc2531bd6a8814bbb6fd57",
      "date": "2025-06-07",
      "startTime": "19:10",
      "category": "band"
    },
    {
      "id": "4e180394c0b4b3add778d587fed12856",
      "bandId": "be5713e3c3ff9b7643f857135f5b0d8c",
      "locationId": "25943ede1bfc2531bd6a8814bbb6fd57",
      "date": "2025-06-07",
      "startTime": "20:40",
      "category": "band"
    },
    {
      "id": "7cfe86b5f1265be2fa9e98ff3f6fcb15",
      "bandId": "df256845c7212af8a6ef1a25d13ba7be",
      "locationId": "25943ede1bfc2531bd6a8814bbb6fd57",
      "date": "2025-06-07",
      "startTime": "22:20",
      "category": "band"
    },
    {
      "id": "c0339f4f81a167b01e471d6d8f4ee42a",
      "bandId": "3b960988ad5d3db50fb9de3da640f998",
      "locationId": "ce206d740f859a7a2e691c7e8a2c1888",
      "date": "2025-06-07",
      "startTime": "17:00",
      "category": "band"
    },
    {
      "id": "8734f87441904fa5764755d2e821b7f8",
      "bandId": "96301feb5097dbc5b165b2b09d1cdeab",
      "locationId": "ce206d740f859a7a2e691c7e8a2c1888",
      "date": "2025-06-07",
      "startTime": "18:20",
      "category": "band"
    },
    {
      "id": "3a76c8859dbb16586719efd277a771d3",
      "bandId": "a5002975613f1711b1e91f046d314f09",
      "locationId": "ce206d740f859a7a2e691c7e8a2c1888",
      "date": "2025-06-07",
      "startTime": "19:40",
      "category": "band"
    },
    {
      "id": "99a65014e7990df5988e1773883b0ef8",
      "bandId": "8b6d6006ec50bab3ab16f803204aa540",
      "locationId": "ce206d740f859a7a2e691c7e8a2c1888",
      "date": "2025-06-07",
      "startTime": "21:00",
      "category": "band"
    },
    {
      "id": "7b26cd047a0f94a21f501c20ac4f5447",
      "bandId": "231c1e12de2d2753790ade9ba85f957a",
      "locationId": "ce206d740f859a7a2e691c7e8a2c1888",
      "date": "2025-06-07",
      "startTime": "22:40",
      "category": "band"
    },
    {
      "id": "3ac7ea34821d16227ed5c8b8daa87053",
      "bandId": "c4782c02d2b8f5cff0fb06a1f253322a",
      "locationId": "a4fa7bae7434338c5143943b5e48efb4",
      "date": "2025-06-07",
      "startTime": "12:00",
      "category": "show"
    },
    {
      "id": "50ad9df39e3fdaafc5331c63b9a2454a",
      "bandId": "9f8ada7f5d9b23f6ee43055645584275",
      "locationId": "a4fa7bae7434338c5143943b5e48efb4",
      "date": "2025-06-07",
      "startTime": "13:00",
      "category": "show"
    },
    {
      "id": "3381166f043242082d16ea9273e575d4",
      "bandId": "a71125a3c3914efa5ebb9b48ec7e8875",
      "locationId": "a4fa7bae7434338c5143943b5e48efb4",
      "date": "2025-06-07",
      "startTime": "14:00",
      "category": "band"
    },
    {
      "id": "0abed1b49872bfc54e576acd113fb7bf",
      "bandId": "e0e52ea2de3d8cbadd16f357c46378cc",
      "locationId": "a4fa7bae7434338c5143943b5e48efb4",
      "date": "2025-06-07",
      "startTime": "15:30",
      "category": "band"
    },
    {
      "id": "3810df728012795db652bd7c53a89037",
      "bandId": "09a9318508da52652852638eacbf39b4",
      "locationId": "a4fa7bae7434338c5143943b5e48efb4",
      "date": "2025-06-07",
      "startTime": "15:30",
      "category": "show"
    },
    {
      "id": "f28e39eb94d6a38b6de3c51caeaaac1c",
      "bandId": "9f8ada7f5d9b23f6ee43055645584275",
      "locationId": "a4fa7bae7434338c5143943b5e48efb4",
      "date": "2025-06-07",
      "startTime": "17:00",
      "category": "show"
    },
    {
      "id": "c7436b2a36563c9cc4724a67b9c31637",
      "bandId": "0c60e0e953f8017c0888d91b25faca43",
      "locationId": "a4fa7bae7434338c5143943b5e48efb4",
      "date": "2025-06-07",
      "startTime": "17:00",
      "category": "band"
    },
    {
      "id": "a392328130fb4244216377bc6955b228",
      "bandId": "0f3adc8652c99ef33b3f945e29a0ac60",
      "locationId": "a4fa7bae7434338c5143943b5e48efb4",
      "date": "2025-06-07",
      "startTime": "18:00",
      "category": "show"
    },
    {
      "id": "b017c913f57f72294043c238bf464498",
      "bandId": "6602e038e68723e86aec013cf835a235",
      "locationId": "a4fa7bae7434338c5143943b5e48efb4",
      "date": "2025-06-07",
      "startTime": "18:30",
      "category": "band"
    },
    {
      "id": "ff108b0670712660516412857640d5a3",
      "bandId": "c75d4ba31f3b96b5a6647cb58620d4a1",
      "locationId": "a4fa7bae7434338c5143943b5e48efb4",
      "date": "2025-06-07",
      "startTime": "19:00",
      "category": "show"
    },
    {
      "id": "84cba8634b93dd70144263d99d035245",
      "bandId": "cd1c06e4da41121b7362540fbe8cd62c",
      "locationId": "a4fa7bae7434338c5143943b5e48efb4",
      "date": "2025-06-07",
      "startTime": "20:05",
      "category": "band"
    },
    {
      "id": "3d26e1ad463803a1b7b1b7a026321908",
      "bandId": "b64884a0464d33488a31b8d3379eb3ff",
      "locationId": "a4fa7bae7434338c5143943b5e48efb4",
      "date": "2025-06-07",
      "startTime": "21:00",
      "category": "show"
    },
    {
      "id": "39d67730b1525dd490a900e09c84cca8",
      "bandId": "23ff1c42312ad5b8bc6e43808e3c66b7",
      "locationId": "a4fa7bae7434338c5143943b5e48efb4",
      "date": "2025-06-07",
      "startTime": "21:45",
      "category": "band"
    },
    {
      "id": "7606aeafb3c59d716e2a1b9dacd2abc3",
      "bandId": "47a9cfcd95a53206e25acb64767e205f",
      "locationId": "a4fa7bae7434338c5143943b5e48efb4",
      "date": "2025-06-07",
      "startTime": "23:30",
      "category": "show"
    },
    {
      "id": "fca924979b3cb73d6d8e723e5984cbb2",
      "bandId": "3759d99006450cddf81cfc0d1bc35e93",
      "locationId": "4eb8b676e4c650a0f196b4ee47ae913d",
      "date": "2025-06-07",
      "startTime": "20:00",
      "category": "band"
    },
    {
      "id": "2dc5cff4e795915114eeb5a450a39405",
      "bandId": "b371a90a02b3b59ad67102d416201ea6",
      "locationId": "4eb8b676e4c650a0f196b4ee47ae913d",
      "date": "2025-06-07",
      "startTime": "21:00",
      "category": "band"
    },
    {
      "id": "357b0b684da41263cdcaa680c10a4ca2",
      "bandId": "573d1b1ab7ba8e60118e4a3331e4e6a1",
      "locationId": "4eb8b676e4c650a0f196b4ee47ae913d",
      "date": "2025-06-07",
      "startTime": "22:00",
      "category": "band"
    },
    {
      "id": "24a685182555452070220a325db33d09",
      "bandId": "3d437671f4b2808ac39679246d25dda3",
      "locationId": "4eb8b676e4c650a0f196b4ee47ae913d",
      "date": "2025-06-07",
      "startTime": "23:10",
      "category": "band"
    },
    {
      "id": "cad400cc13f0544abd6e0be833dae664",
      "bandId": "d351305da15101130ba38d253fe3d1c1",
      "locationId": "ddc89946f8e5b850cd1a5742406c6c87",
      "date": "2025-06-07",
      "startTime": "17:30",
      "category": "band"
    },
    {
      "id": "828c1b518cdc57d11d723da431b38261",
      "bandId": "4272f0f2e28856b74a4a6774d55a8758",
      "locationId": "ddc89946f8e5b850cd1a5742406c6c87",
      "date": "2025-06-07",
      "startTime": "20:00",
      "category": "band"
    },
    {
      "id": "cbddaeb656547c48491e5b6d8a45915c",
      "bandId": "7386bc0fc4b9453a37ebe39b6883b219",
      "locationId": "ddc89946f8e5b850cd1a5742406c6c87",
      "date": "2025-06-07",
      "startTime": "22:30",
      "category": "band"
    },
    {
      "id": "42620b3ef9ee7be645c8cacb757aa7d8",
      "bandId": "a3a7c1b0c87edd3357abc7cbab368b88",
      "locationId": "16bdce7af743ea1b04aef7d4dcefecd0",
      "date": "2025-06-07",
      "startTime": "16:25",
      "category": "band"
    },
    {
      "id": "04c510699800d8ae28759c2e9fb9ac53",
      "bandId": "096f9d5d65e2ffd0fcfd7a9b6b1494d8",
      "locationId": "16bdce7af743ea1b04aef7d4dcefecd0",
      "date": "2025-06-07",
      "startTime": "18:45",
      "category": "band"
    },
    {
      "id": "dffd1c4ec182170f2a30a4d21d7b7ade",
      "bandId": "f849c957f2c50579eb4d85c468427be5",
      "locationId": "16bdce7af743ea1b04aef7d4dcefecd0",
      "date": "2025-06-07",
      "startTime": "21:15",
      "category": "band"
    },
    {
      "id": "83e1487810bea325ef78c0b857b1cbe2",
      "bandId": "f62a95c25171543afbf8de2764df5a1d",
      "locationId": "9c3e9e09a83273d69f49c4c39006941c",
      "date": "2025-06-07",
      "startTime": "17:00",
      "category": "band"
    },
    {
      "id": "cd071d4d24ca41dd7e680395fa36d4bf",
      "bandId": "fc31f5e2ceb6a2ee9ec213761aa00caf",
      "locationId": "9c3e9e09a83273d69f49c4c39006941c",
      "date": "2025-06-07",
      "startTime": "18:20",
      "category": "band"
    },
    {
      "id": "2b51157481a04a96638e33d5b021f836",
      "bandId": "0c12da5fb58bfc10d8f6d2e6f28f50fd",
      "locationId": "9c3e9e09a83273d69f49c4c39006941c",
      "date": "2025-06-07",
      "startTime": "19:50",
      "category": "band"
    },
    {
      "id": "4712a33456403bc1b1532749cf565315",
      "bandId": "922a7010bd95e72ec7635c5942c4a449",
      "locationId": "9c3e9e09a83273d69f49c4c39006941c",
      "date": "2025-06-07",
      "startTime": "21:10",
      "category": "band"
    },
    {
      "id": "3bf6e321d12f0e7b25a3caebf2cd9bd1",
      "bandId": "03168ab0bd5ed4c8125c88ab3b02a8f2",
      "locationId": "9c3e9e09a83273d69f49c4c39006941c",
      "date": "2025-06-07",
      "startTime": "22:40",
      "category": "band"
    },
    {
      "id": "e806dda49f1245a253e73272f5d4f5c5",
      "bandId": "a3e6115fc85d91de3878bacfd80dbea0",
      "locationId": "a4df6f5c5655dd443bdaa2ac28ec6105",
      "date": "2025-06-07",
      "startTime": "16:30",
      "category": "band"
    },
    {
      "id": "695bc942a613a77e901ebbb5d8129263",
      "bandId": "d78bcaac146002037edd94626a00d060",
      "locationId": "a4df6f5c5655dd443bdaa2ac28ec6105",
      "date": "2025-06-07",
      "startTime": "17:50",
      "category": "band"
    },
    {
      "id": "8faee2686d50b4b101ca226c9ee609a0",
      "bandId": "b57859ba1abaebac6ad9e3121c84a708",
      "locationId": "a4df6f5c5655dd443bdaa2ac28ec6105",
      "date": "2025-06-07",
      "startTime": "19:10",
      "category": "band"
    },
    {
      "id": "f55c3fa85c6c769c43626572f1577cb6",
      "bandId": "512a1e4bde5d9c3949612672fb95891a",
      "locationId": "a4df6f5c5655dd443bdaa2ac28ec6105",
      "date": "2025-06-07",
      "startTime": "20:40",
      "category": "band"
    },
    {
      "id": "cce122f9118c115019c5c34bfa52fcf9",
      "bandId": "c15d401e7380b4ac09db839cc369da93",
      "locationId": "a4df6f5c5655dd443bdaa2ac28ec6105",
      "date": "2025-06-07",
      "startTime": "22:20",
      "category": "band"
    },
    {
      "id": "9f7ba8b85d1bafd259244704f2616318",
      "bandId": "531ac363659e2b48c5794282bb6b32b4",
      "locationId": "f9de432063e814bcb67ea92bf3713fdb",
      "date": "2025-06-07",
      "startTime": "16:00",
      "category": "band"
    },
    {
      "id": "e5b73a2ea126564ecc979e2a2fb5380a",
      "bandId": "b549689b6e61e488dc4087527f392beb",
      "locationId": "5fe101bcd2edae028474473e52b9751f",
      "date": "2025-06-07",
      "startTime": "13:00",
      "category": "show"
    },
    {
      "id": "f77f0617a0f76251fb37aed0f0ef0a5e",
      "bandId": "c63728ab1da64d43804195dc96a86037",
      "locationId": "5fe101bcd2edae028474473e52b9751f",
      "date": "2025-06-07",
      "startTime": "14:00",
      "category": "show"
    },
    {
      "id": "275e31ae26cce88d216973180baec2cf",
      "bandId": "b14bdd2dcfb3711634da80b079ef9168",
      "locationId": "5fe101bcd2edae028474473e52b9751f",
      "date": "2025-06-07",
      "startTime": "15:00",
      "category": "show"
    },
    {
      "id": "42515e3d5c875353987a31ef924c06bf",
      "bandId": "ed482c72dc88d7297d3ce61f7a2d3742",
      "locationId": "5fe101bcd2edae028474473e52b9751f",
      "date": "2025-06-07",
      "startTime": "16:00",
      "category": "show"
    },
    {
      "id": "b624cf9ba3cf9dcf9cfb4c4ffafb2b00",
      "bandId": "b549689b6e61e488dc4087527f392beb",
      "locationId": "5fe101bcd2edae028474473e52b9751f",
      "date": "2025-06-07",
      "startTime": "17:00",
      "category": "show"
    },
    {
      "id": "023f3eeecaea9caad6dca06681c98ad6",
      "bandId": "b14bdd2dcfb3711634da80b079ef9168",
      "locationId": "5fe101bcd2edae028474473e52b9751f",
      "date": "2025-06-07",
      "startTime": "18:00",
      "category": "show"
    },
    {
      "id": "e6d40874918192f346344fbc439c818f",
      "bandId": "b549689b6e61e488dc4087527f392beb",
      "locationId": "5fe101bcd2edae028474473e52b9751f",
      "date": "2025-06-07",
      "startTime": "19:00",
      "category": "show"
    },
    {
      "id": "f10053db62be841f3b483852bdcdef95",
      "bandId": "b14bdd2dcfb3711634da80b079ef9168",
      "locationId": "5fe101bcd2edae028474473e52b9751f",
      "date": "2025-06-07",
      "startTime": "20:00",
      "category": "show"
    },
    {
      "id": "918f76fb7ffe159c8834c6ab9f7c994a",
      "bandId": "5c4eb1ff35b815c9cde6cd2110dca1db",
      "locationId": "5fe101bcd2edae028474473e52b9751f",
      "date": "2025-06-07",
      "startTime": "21:00",
      "category": "show"
    },
    {
      "id": "d6757c30bbb0ae44172fd9ce3f7c11a4",
      "bandId": "41dff6cb80483b0c4408f47b9aa32875",
      "locationId": "59c80748f493ceecd0d76b57ebe2de2e",
      "date": "2025-06-08",
      "startTime": "17:00",
      "category": "band"
    },
    {
      "id": "64a285336f4b6f806e9af22c9fa6dbf8",
      "bandId": "eb62af7492157c676fb8fc9692e83447",
      "locationId": "59c80748f493ceecd0d76b57ebe2de2e",
      "date": "2025-06-08",
      "startTime": "18:15",
      "category": "band"
    },
    {
      "id": "0dd214fbd749817825a3cb367f29a10e",
      "bandId": "534982fddde518d146945176d145cd12",
      "locationId": "59c80748f493ceecd0d76b57ebe2de2e",
      "date": "2025-06-08",
      "startTime": "19:40",
      "category": "band"
    },
    {
      "id": "4d51a18497a708b984eaaca10f1e0beb",
      "bandId": "143af26de9d57bf624771616318aaf7c",
      "locationId": "59c80748f493ceecd0d76b57ebe2de2e",
      "date": "2025-06-08",
      "startTime": "21:20",
      "category": "band"
    },
    {
      "id": "9893f20619df84c4f23c362a8b65d17d",
      "bandId": "50ab5192d58b8dc6fd76129ebc416238",
      "locationId": "59c80748f493ceecd0d76b57ebe2de2e",
      "date": "2025-06-08",
      "startTime": "23:00",
      "category": "band"
    },
    {
      "id": "0fc814f0700dba55699e1f0112ac6e90",
      "bandId": "1da6407d4b67c0196e5076d3817ad491",
      "locationId": "59c80748f493ceecd0d76b57ebe2de2e",
      "date": "2025-06-09",
      "startTime": "01:00",
      "category": "band"
    },
    {
      "id": "fd419896bc9a3870fc76d9a6e4168e8a",
      "bandId": "dbd9414e22c006289473493a6d1389f8",
      "locationId": "25943ede1bfc2531bd6a8814bbb6fd57",
      "date": "2025-06-08",
      "startTime": "16:30",
      "category": "band"
    },
    {
      "id": "766ee370d16fd1a2657a1b6fbb396ad6",
      "bandId": "af2cd7cf14f5b9165b0b074aea349a21",
      "locationId": "25943ede1bfc2531bd6a8814bbb6fd57",
      "date": "2025-06-08",
      "startTime": "17:50",
      "category": "band"
    },
    {
      "id": "31fc4a48abb60acb23ae52aecbdf0ed8",
      "bandId": "747677bc2da67e70ff5c1a900b35fbab",
      "locationId": "25943ede1bfc2531bd6a8814bbb6fd57",
      "date": "2025-06-08",
      "startTime": "19:10",
      "category": "band"
    },
    {
      "id": "0af0d4dadb3ff1be0569bce90e70b484",
      "bandId": "f6237bec3009c68bfe45b6553f354fed",
      "locationId": "25943ede1bfc2531bd6a8814bbb6fd57",
      "date": "2025-06-08",
      "startTime": "20:40",
      "category": "band"
    },
    {
      "id": "27a9c3494c08a05a7900252b2ba0332a",
      "bandId": "1bbdbbc1be9859edf9ae00fa9f2da113",
      "locationId": "25943ede1bfc2531bd6a8814bbb6fd57",
      "date": "2025-06-08",
      "startTime": "22:20",
      "category": "band"
    },
    {
      "id": "8032ed4621263ff2a1048df36791ed1d",
      "bandId": "ba628e6419eeafc36eda4cb2ca6e3492",
      "locationId": "ce206d740f859a7a2e691c7e8a2c1888",
      "date": "2025-06-08",
      "startTime": "17:00",
      "category": "band"
    },
    {
      "id": "c76f216ca4c6e092d8d0a9cc395993e4",
      "bandId": "3af2ee7fa80839fdd552e3f55c244ac7",
      "locationId": "ce206d740f859a7a2e691c7e8a2c1888",
      "date": "2025-06-08",
      "startTime": "18:20",
      "category": "band"
    },
    {
      "id": "6fbcb5dd0dbf8c73f1ee55e1f648b73b",
      "bandId": "57e949565f9d4fc031ecac41915b25ef",
      "locationId": "ce206d740f859a7a2e691c7e8a2c1888",
      "date": "2025-06-08",
      "startTime": "19:40",
      "category": "band"
    },
    {
      "id": "d7cf1f6dbca412b581718242c318c7aa",
      "bandId": "d37dc1d462431c21ab36855d98590bf2",
      "locationId": "ce206d740f859a7a2e691c7e8a2c1888",
      "date": "2025-06-08",
      "startTime": "21:00",
      "category": "band"
    },
    {
      "id": "a18ad8484197bc24c97d8e2f1d83bef3",
      "bandId": "5d98c40222b27767c2639dd5d4f2cbbd",
      "locationId": "ce206d740f859a7a2e691c7e8a2c1888",
      "date": "2025-06-08",
      "startTime": "22:30",
      "category": "band"
    },
    {
      "id": "87c1d6e6292e3179c6d6521d470364aa",
      "bandId": "c4782c02d2b8f5cff0fb06a1f253322a",
      "locationId": "a4fa7bae7434338c5143943b5e48efb4",
      "date": "2025-06-08",
      "startTime": "12:00",
      "category": "show"
    },
    {
      "id": "5e3f5571d21ff41edcd2378bf8373264",
      "bandId": "9f8ada7f5d9b23f6ee43055645584275",
      "locationId": "a4fa7bae7434338c5143943b5e48efb4",
      "date": "2025-06-08",
      "startTime": "13:00",
      "category": "show"
    },
    {
      "id": "de8eda7439188f2e4300c79401aa82c2",
      "bandId": "572fad4f58b156b713e8e6ff4c58cc5b",
      "locationId": "a4fa7bae7434338c5143943b5e48efb4",
      "date": "2025-06-08",
      "startTime": "14:00",
      "category": "band"
    },
    {
      "id": "3d359e525ab67f7c73c2f5fc70a62fb2",
      "bandId": "93ddc62e1b13b6ffbaf5faacf4a45a28",
      "locationId": "a4fa7bae7434338c5143943b5e48efb4",
      "date": "2025-06-08",
      "startTime": "14:15",
      "category": "show"
    },
    {
      "id": "388993507ae3eeaf2a9e57c0153ad923",
      "bandId": "09a9318508da52652852638eacbf39b4",
      "locationId": "a4fa7bae7434338c5143943b5e48efb4",
      "date": "2025-06-08",
      "startTime": "15:00",
      "category": "show"
    },
    {
      "id": "f4e5cb610b83e9a21ffc28d7f79af065",
      "bandId": "48e2ca1c28ae9e7dadcda6ad935da2ed",
      "locationId": "a4fa7bae7434338c5143943b5e48efb4",
      "date": "2025-06-08",
      "startTime": "15:50",
      "category": "band"
    },
    {
      "id": "9aa2c0d2633275315f480623603dd6aa",
      "bandId": "9f8ada7f5d9b23f6ee43055645584275",
      "locationId": "a4fa7bae7434338c5143943b5e48efb4",
      "date": "2025-06-08",
      "startTime": "16:00",
      "category": "show"
    },
    {
      "id": "3836e315d3f9716ff8595c02d15432f1",
      "bandId": "93ddc62e1b13b6ffbaf5faacf4a45a28",
      "locationId": "a4fa7bae7434338c5143943b5e48efb4",
      "date": "2025-06-08",
      "startTime": "17:00",
      "category": "show"
    },
    {
      "id": "45866cf87d9dcbc5d928a748b86dec97",
      "bandId": "d69462bef6601bb8d6e3ffda067399d9",
      "locationId": "a4fa7bae7434338c5143943b5e48efb4",
      "date": "2025-06-08",
      "startTime": "17:30",
      "category": "band"
    },
    {
      "id": "91de5fa2eeaeb27d357cf3b786db48f1",
      "bandId": "9f8ada7f5d9b23f6ee43055645584275",
      "locationId": "a4fa7bae7434338c5143943b5e48efb4",
      "date": "2025-06-08",
      "startTime": "18:00",
      "category": "show"
    },
    {
      "id": "87a5f4f560b1698587b9c286c3d842b4",
      "bandId": "c75d4ba31f3b96b5a6647cb58620d4a1",
      "locationId": "a4fa7bae7434338c5143943b5e48efb4",
      "date": "2025-06-08",
      "startTime": "19:00",
      "category": "show"
    },
    {
      "id": "c6cb58f55ee7ddecec0648634fb18f24",
      "bandId": "f3d7662a9107de0635f647b83ae55566",
      "locationId": "a4fa7bae7434338c5143943b5e48efb4",
      "date": "2025-06-08",
      "startTime": "19:20",
      "category": "band"
    },
    {
      "id": "a4eaa382d73e22568d2ebdabf16a88fb",
      "bandId": "f10f1ea9e6a334fe99c69ad0102908f9",
      "locationId": "a4fa7bae7434338c5143943b5e48efb4",
      "date": "2025-06-08",
      "startTime": "20:00",
      "category": "show"
    },
    {
      "id": "82c257c9b9e0f190cdd49115c74134f5",
      "bandId": "93ddc62e1b13b6ffbaf5faacf4a45a28",
      "locationId": "a4fa7bae7434338c5143943b5e48efb4",
      "date": "2025-06-08",
      "startTime": "21:00",
      "category": "show"
    },
    {
      "id": "89598f4738c0096ec5821e6a4e0c75ce",
      "bandId": "f65d3d938f139227d9f22ad3d3a473df",
      "locationId": "a4fa7bae7434338c5143943b5e48efb4",
      "date": "2025-06-08",
      "startTime": "21:20",
      "category": "band"
    },
    {
      "id": "7cd79164efb584a9cb0c1f8a343255c9",
      "bandId": "47a9cfcd95a53206e25acb64767e205f",
      "locationId": "a4fa7bae7434338c5143943b5e48efb4",
      "date": "2025-06-08",
      "startTime": "23:30",
      "category": "show"
    },
    {
      "id": "fb872007dc5e6333361bffc1ed7ce439",
      "bandId": "281a836af1e09e8b25fdd84c5a882954",
      "locationId": "4eb8b676e4c650a0f196b4ee47ae913d",
      "date": "2025-06-08",
      "startTime": "20:00",
      "category": "band"
    },
    {
      "id": "ad73643b60045f28dbd4212b2604b974",
      "bandId": "833a28074b156b57b538cc1332589c7b",
      "locationId": "4eb8b676e4c650a0f196b4ee47ae913d",
      "date": "2025-06-08",
      "startTime": "21:00",
      "category": "band"
    },
    {
      "id": "ff74ccb107eb7109819180985737ed7e",
      "bandId": "733c98ccb843041211b866fe9a699faf",
      "locationId": "4eb8b676e4c650a0f196b4ee47ae913d",
      "date": "2025-06-08",
      "startTime": "22:00",
      "category": "band"
    },
    {
      "id": "c0e770f700401a56ec4ad23c313ed859",
      "bandId": "4dda4f48c7a4b87d8295b482a567d511",
      "locationId": "4eb8b676e4c650a0f196b4ee47ae913d",
      "date": "2025-06-08",
      "startTime": "23:10",
      "category": "band"
    },
    {
      "id": "29d128d5e9f2cfc408f0bfe6cad09a66",
      "bandId": "4a0b3fae795fdebddaa303ad85096ebd",
      "locationId": "ddc89946f8e5b850cd1a5742406c6c87",
      "date": "2025-06-08",
      "startTime": "17:30",
      "category": "band"
    },
    {
      "id": "8aeafdcb26298fa1f3ded30b8dd409b7",
      "bandId": "02e2007a30a2439074c584e125328e23",
      "locationId": "ddc89946f8e5b850cd1a5742406c6c87",
      "date": "2025-06-08",
      "startTime": "20:00",
      "category": "band"
    },
    {
      "id": "fce9729b5b9f207c84c5a5a69aca3814",
      "bandId": "1d4042750dd8d231fdc0d39ce58f664c",
      "locationId": "ddc89946f8e5b850cd1a5742406c6c87",
      "date": "2025-06-08",
      "startTime": "22:30",
      "category": "band"
    },
    {
      "id": "5cb480d8bc1a9f87348b49a570ba952e",
      "bandId": "8fbb28f1334219a3ac918273f7690c4e",
      "locationId": "16bdce7af743ea1b04aef7d4dcefecd0",
      "date": "2025-06-08",
      "startTime": "18:45",
      "category": "band"
    },
    {
      "id": "c0cd3dfa575345baf558a201baedc73e",
      "bandId": "a277e254800234eeb726a345de2b4e5f",
      "locationId": "16bdce7af743ea1b04aef7d4dcefecd0",
      "date": "2025-06-08",
      "startTime": "21:15",
      "category": "band"
    },
    {
      "id": "9ae6c0b77e3813f7740c6f481754d034",
      "bandId": "df256845c7212af8a6ef1a25d13ba7be",
      "locationId": "ee531432311a801a59d6a2cef8c1f6fc",
      "date": "2025-06-08",
      "startTime": "16:00",
      "category": "band"
    },
    {
      "id": "a7c27e6752056c66b6c1633a8044cf4d",
      "bandId": "9945003528c4ef2ca61e3cea99bb2250",
      "locationId": "ee531432311a801a59d6a2cef8c1f6fc",
      "date": "2025-06-08",
      "startTime": "18:00",
      "category": "band"
    },
    {
      "id": "f71425de88692218b55c9d9d79e4df32",
      "bandId": "ae860b11ae80b4642e8a9fb24050b490",
      "locationId": "9c3e9e09a83273d69f49c4c39006941c",
      "date": "2025-06-08",
      "startTime": "17:00",
      "category": "band"
    },
    {
      "id": "35c8533deb024ec448a379d01b25eb54",
      "bandId": "92a2a0896f3ef8ba4ce2368a23836f10",
      "locationId": "9c3e9e09a83273d69f49c4c39006941c",
      "date": "2025-06-08",
      "startTime": "18:20",
      "category": "band"
    },
    {
      "id": "9218234ede994ff826f89ac44ba8053c",
      "bandId": "88a9444a8827772b59b4ca7f61cb88e6",
      "locationId": "9c3e9e09a83273d69f49c4c39006941c",
      "date": "2025-06-08",
      "startTime": "19:40",
      "category": "band"
    },
    {
      "id": "41c180fd4368d7d25e2a01ab3f9de165",
      "bandId": "1ef78d40643f4e530d8742462c69449e",
      "locationId": "9c3e9e09a83273d69f49c4c39006941c",
      "date": "2025-06-08",
      "startTime": "21:10",
      "category": "band"
    },
    {
      "id": "d9d785deef2a7e7d3e7f86220eead1ae",
      "bandId": "23bcc024a0a6c53546d6fdd25b1673ee",
      "locationId": "9c3e9e09a83273d69f49c4c39006941c",
      "date": "2025-06-08",
      "startTime": "22:40",
      "category": "band"
    },
    {
      "id": "58aa9e88066637f364e116a4c76fa821",
      "bandId": "023699fca54ef93f1d3be05bb9a9fa7d",
      "locationId": "a4df6f5c5655dd443bdaa2ac28ec6105",
      "date": "2025-06-08",
      "startTime": "16:30",
      "category": "band"
    },
    {
      "id": "769dca181a72a908359afa19e698f2ef",
      "bandId": "080e22165203b5c3d7d8d46c6268e98a",
      "locationId": "a4df6f5c5655dd443bdaa2ac28ec6105",
      "date": "2025-06-08",
      "startTime": "17:50",
      "category": "band"
    },
    {
      "id": "783d2d59c3eca3d208d39d66913b86a9",
      "bandId": "b35ef33f378d58502ae84288d791a463",
      "locationId": "a4df6f5c5655dd443bdaa2ac28ec6105",
      "date": "2025-06-08",
      "startTime": "19:10",
      "category": "band"
    },
    {
      "id": "8e6aa982828f5bea31bd1fd3acc24fd4",
      "bandId": "9dc73fe924bb17caae376ec76afa5d0d",
      "locationId": "a4df6f5c5655dd443bdaa2ac28ec6105",
      "date": "2025-06-08",
      "startTime": "20:40",
      "category": "band"
    },
    {
      "id": "bbd68af0c3e541910c13e20dda66114e",
      "bandId": "db5c9ed3e471212d45cdd6c321066d60",
      "locationId": "a4df6f5c5655dd443bdaa2ac28ec6105",
      "date": "2025-06-08",
      "startTime": "22:20",
      "category": "band"
    },
    {
      "id": "0e953feadf7976f71046c8563adca0f7",
      "bandId": "d32f061033ed3864c079c82ee2e6e045",
      "locationId": "2a55f3eca82c7bfb32506bcf7d3c1561",
      "date": "2025-06-08",
      "startTime": "16:35",
      "category": "band"
    },
    {
      "id": "75d1f77c950dc3a6d489917c0292b8c5",
      "bandId": "97036da18452da08c0bbd821411df1bf",
      "locationId": "2a55f3eca82c7bfb32506bcf7d3c1561",
      "date": "2025-06-08",
      "startTime": "18:45",
      "category": "band"
    },
    {
      "id": "9bb5c6dbaf75750afa5b7e4d27691354",
      "bandId": "7054b6f3ca314c758037dfda2432d39e",
      "locationId": "2a55f3eca82c7bfb32506bcf7d3c1561",
      "date": "2025-06-08",
      "startTime": "21:15",
      "category": "band"
    },
    {
      "id": "a76a211866b87ee38ca5ac3743804472",
      "bandId": "33981a59ed065b4fa9fe1b0e24230949",
      "locationId": "f9de432063e814bcb67ea92bf3713fdb",
      "date": "2025-06-08",
      "startTime": "15:30",
      "category": "band"
    },
    {
      "id": "2a26ca1ad0da87c3a32d66bb13d1dd53",
      "bandId": "216f70178e7f3577a557612c606b5993",
      "locationId": "f9de432063e814bcb67ea92bf3713fdb",
      "date": "2025-06-08",
      "startTime": "17:40",
      "category": "band"
    },
    {
      "id": "8ddfa1dcb9d530996d689ca81b95f1c3",
      "bandId": "f2ea9a7dfdcaaac59523b2babe7d018e",
      "locationId": "f9de432063e814bcb67ea92bf3713fdb",
      "date": "2025-06-08",
      "startTime": "19:50",
      "category": "band"
    },
    {
      "id": "af5ae856fba3bb0a81363e20f94a0c1f",
      "bandId": "b0ab75d3f09f8edf3579ea58aae3571b",
      "locationId": "f9de432063e814bcb67ea92bf3713fdb",
      "date": "2025-06-08",
      "startTime": "22:30",
      "category": "band"
    },
    {
      "id": "ed8f22888767547d3637663cee022fa3",
      "bandId": "26d62c17c1bda3adecc4c5b136ac0318",
      "locationId": "5fe101bcd2edae028474473e52b9751f",
      "date": "2025-06-08",
      "startTime": "13:00",
      "category": "show"
    },
    {
      "id": "f931b173ee759ce789b6320ba024a6da",
      "bandId": "c63728ab1da64d43804195dc96a86037",
      "locationId": "5fe101bcd2edae028474473e52b9751f",
      "date": "2025-06-08",
      "startTime": "14:00",
      "category": "show"
    },
    {
      "id": "66720a1f1819b12c59d8d05fbbdf6ba7",
      "bandId": "26d62c17c1bda3adecc4c5b136ac0318",
      "locationId": "5fe101bcd2edae028474473e52b9751f",
      "date": "2025-06-08",
      "startTime": "15:00",
      "category": "show"
    },
    {
      "id": "6438a289e787fc66bd2e64cd77788a78",
      "bandId": "c63728ab1da64d43804195dc96a86037",
      "locationId": "5fe101bcd2edae028474473e52b9751f",
      "date": "2025-06-08",
      "startTime": "16:00",
      "category": "show"
    },
    {
      "id": "01434d00f3b2a7bcc03114b3bef80fa8",
      "bandId": "26d62c17c1bda3adecc4c5b136ac0318",
      "locationId": "5fe101bcd2edae028474473e52b9751f",
      "date": "2025-06-08",
      "startTime": "17:00",
      "category": "show"
    },
    {
      "id": "8a274a27af495094e53b84928472c782",
      "bandId": "62b1a15d39a5fc95e1fa28b2af2f10ba",
      "locationId": "5fe101bcd2edae028474473e52b9751f",
      "date": "2025-06-08",
      "startTime": "18:00",
      "category": "show"
    },
    {
      "id": "c479e8c5e7bfe1f9676b015c0c9c9298",
      "bandId": "26d62c17c1bda3adecc4c5b136ac0318",
      "locationId": "5fe101bcd2edae028474473e52b9751f",
      "date": "2025-06-08",
      "startTime": "19:00",
      "category": "show"
    },
    {
      "id": "a20b2575157068536b2b3efc47ec578d",
      "bandId": "5c4eb1ff35b815c9cde6cd2110dca1db",
      "locationId": "5fe101bcd2edae028474473e52b9751f",
      "date": "2025-06-08",
      "startTime": "21:00",
      "category": "show"
    },
    {
      "id": "9ae651f4b0cf691a89daaf435731b05a",
      "bandId": "ccdc1d2d7618e67e0c2b08b4ff9fd8f0",
      "locationId": "59c80748f493ceecd0d76b57ebe2de2e",
      "date": "2025-06-09",
      "startTime": "17:00",
      "category": "band"
    },
    {
      "id": "f263babe8bdcdcc554d034f0935c9d23",
      "bandId": "63bd91393913705437d42a3a7bf4535b",
      "locationId": "59c80748f493ceecd0d76b57ebe2de2e",
      "date": "2025-06-09",
      "startTime": "18:30",
      "category": "band"
    },
    {
      "id": "755b2ff0bf1d551ed8a1f9eea9f87c92",
      "bandId": "8227ff91b5086c88e66f991aa6f0371b",
      "locationId": "59c80748f493ceecd0d76b57ebe2de2e",
      "date": "2025-06-09",
      "startTime": "19:55",
      "category": "band"
    },
    {
      "id": "4742182423a216588a8532fca3776f06",
      "bandId": "98f5c5baf32215e003244fcf2cace66a",
      "locationId": "59c80748f493ceecd0d76b57ebe2de2e",
      "date": "2025-06-09",
      "startTime": "21:20",
      "category": "band"
    },
    {
      "id": "ca05d2f91c84434279b59cc02d95b5bc",
      "bandId": "191cfb6f9caecb6571a1782954e8205e",
      "locationId": "59c80748f493ceecd0d76b57ebe2de2e",
      "date": "2025-06-09",
      "startTime": "22:45",
      "category": "band"
    },
    {
      "id": "77d17315493cb817bac27a4a54917cd3",
      "bandId": "510ddd5524ab16d583d8b7317a55f474",
      "locationId": "25943ede1bfc2531bd6a8814bbb6fd57",
      "date": "2025-06-09",
      "startTime": "16:30",
      "category": "band"
    },
    {
      "id": "ae612c46d36c45642b4d7606d4f2c6f4",
      "bandId": "1a1a2554ec1a79500fb68b972ba44ed6",
      "locationId": "25943ede1bfc2531bd6a8814bbb6fd57",
      "date": "2025-06-09",
      "startTime": "17:50",
      "category": "band"
    },
    {
      "id": "7a9b20d20914bd59993fbfda005e2cfa",
      "bandId": "f0520a57e6e312d5917bfd2a3a943b35",
      "locationId": "25943ede1bfc2531bd6a8814bbb6fd57",
      "date": "2025-06-09",
      "startTime": "19:10",
      "category": "band"
    },
    {
      "id": "ba87c555662eaefaea62f764c065e66c",
      "bandId": "71c982b9a58f293b1b3778705e67574b",
      "locationId": "25943ede1bfc2531bd6a8814bbb6fd57",
      "date": "2025-06-09",
      "startTime": "20:40",
      "category": "band"
    },
    {
      "id": "32492cab49648026b81b6b200e31ae6c",
      "bandId": "e82f40d2f4df9dd006ff8557e0f85691",
      "locationId": "25943ede1bfc2531bd6a8814bbb6fd57",
      "date": "2025-06-09",
      "startTime": "22:20",
      "category": "band"
    },
    {
      "id": "1258c178c5d8413a8f52ee0ad02d5d8a",
      "bandId": "2e8850d6645fff92c503e26b88ab61c3",
      "locationId": "ce206d740f859a7a2e691c7e8a2c1888",
      "date": "2025-06-09",
      "startTime": "17:00",
      "category": "band"
    },
    {
      "id": "98e992da482a44e69ef895c04c010d7a",
      "bandId": "87ba7b5c0de45056bb36cd27d80b072c",
      "locationId": "ce206d740f859a7a2e691c7e8a2c1888",
      "date": "2025-06-09",
      "startTime": "18:20",
      "category": "band"
    },
    {
      "id": "16718a6b6edaa2f8d8752e34e8a688cd",
      "bandId": "1e7c41955052e131a4f4e6d82161dc01",
      "locationId": "ce206d740f859a7a2e691c7e8a2c1888",
      "date": "2025-06-09",
      "startTime": "19:40",
      "category": "band"
    },
    {
      "id": "2056bedea54ae7a386ef9313156be57c",
      "bandId": "bab198e4a30f6eeb50756bfbb0579227",
      "locationId": "ce206d740f859a7a2e691c7e8a2c1888",
      "date": "2025-06-09",
      "startTime": "21:10",
      "category": "band"
    },
    {
      "id": "a13da505bded7b52dde19e83afc5beb4",
      "bandId": "93ddc62e1b13b6ffbaf5faacf4a45a28",
      "locationId": "a4fa7bae7434338c5143943b5e48efb4",
      "date": "2025-06-09",
      "startTime": "12:00",
      "category": "show"
    },
    {
      "id": "05673fb7b19da9daf81208f18141275e",
      "bandId": "c4782c02d2b8f5cff0fb06a1f253322a",
      "locationId": "a4fa7bae7434338c5143943b5e48efb4",
      "date": "2025-06-09",
      "startTime": "13:00",
      "category": "show"
    },
    {
      "id": "432516c514b270d5b7526790a3b628bb",
      "bandId": "54331b9b16e65e2658e391486720d69f",
      "locationId": "a4fa7bae7434338c5143943b5e48efb4",
      "date": "2025-06-09",
      "startTime": "14:00",
      "category": "band"
    },
    {
      "id": "930de5e21ce5895dc40106648c18a366",
      "bandId": "09a9318508da52652852638eacbf39b4",
      "locationId": "a4fa7bae7434338c5143943b5e48efb4",
      "date": "2025-06-09",
      "startTime": "14:00",
      "category": "show"
    },
    {
      "id": "d487739b6d8cba7aeabf90f3cf21e2eb",
      "bandId": "b64884a0464d33488a31b8d3379eb3ff",
      "locationId": "a4fa7bae7434338c5143943b5e48efb4",
      "date": "2025-06-09",
      "startTime": "15:00",
      "category": "show"
    },
    {
      "id": "c910bce23839818099d0b0867b6ee53c",
      "bandId": "bc77f9a10f311a432c65bdd4c56eca7f",
      "locationId": "a4fa7bae7434338c5143943b5e48efb4",
      "date": "2025-06-09",
      "startTime": "15:30",
      "category": "band"
    },
    {
      "id": "b0949b762a87cd16efb47b26c1d18924",
      "bandId": "c75d4ba31f3b96b5a6647cb58620d4a1",
      "locationId": "a4fa7bae7434338c5143943b5e48efb4",
      "date": "2025-06-09",
      "startTime": "16:00",
      "category": "show"
    },
    {
      "id": "2803f51993e8e175f36a805d65750bcf",
      "bandId": "93ddc62e1b13b6ffbaf5faacf4a45a28",
      "locationId": "a4fa7bae7434338c5143943b5e48efb4",
      "date": "2025-06-09",
      "startTime": "17:00",
      "category": "show"
    },
    {
      "id": "7e1c79db147fdaeab39ef3cce2faac24",
      "bandId": "8403aed2db8164a17046f4d61a8e8e77",
      "locationId": "a4fa7bae7434338c5143943b5e48efb4",
      "date": "2025-06-09",
      "startTime": "17:20",
      "category": "band"
    },
    {
      "id": "3c3ed833281904786ec454c147f61395",
      "bandId": "de26f58f2892752a1c10cadcee7388ec",
      "locationId": "a4fa7bae7434338c5143943b5e48efb4",
      "date": "2025-06-09",
      "startTime": "18:00",
      "category": "show"
    },
    {
      "id": "c087cef2c69ac3bf85b10a2f6adf0236",
      "bandId": "259e1392c7248aa73739b0d44ed805a9",
      "locationId": "a4fa7bae7434338c5143943b5e48efb4",
      "date": "2025-06-09",
      "startTime": "19:15",
      "category": "band"
    },
    {
      "id": "ac6fba3313142062a3ad8a6b733fda1c",
      "bandId": "ac47baa2169b8473568fe45652c24bf8",
      "locationId": "4eb8b676e4c650a0f196b4ee47ae913d",
      "date": "2025-06-09",
      "startTime": "19:30",
      "category": "band"
    },
    {
      "id": "4694c6cc30a5abe2ad14db6977706db2",
      "bandId": "8ad41aa0f71854f2aee6b67300ccd420",
      "locationId": "4eb8b676e4c650a0f196b4ee47ae913d",
      "date": "2025-06-09",
      "startTime": "20:30",
      "category": "band"
    },
    {
      "id": "0f6c1bcda052ab7f92cdb0b58d2606f8",
      "bandId": "cc87aa9f484bf88cd9db2f9c8deb8916",
      "locationId": "4eb8b676e4c650a0f196b4ee47ae913d",
      "date": "2025-06-09",
      "startTime": "21:30",
      "category": "band"
    },
    {
      "id": "4533f3af6bd03b289b12f356d76f02a5",
      "bandId": "3d09ea3d53516ab906a53ae0bb938943",
      "locationId": "4eb8b676e4c650a0f196b4ee47ae913d",
      "date": "2025-06-09",
      "startTime": "22:40",
      "category": "band"
    },
    {
      "id": "57834e408d90d507c9031dd557bbd84f",
      "bandId": "39841b789f8c4837496688100c4c3efd",
      "locationId": "a4df6f5c5655dd443bdaa2ac28ec6105",
      "date": "2025-06-09",
      "startTime": "16:30",
      "category": "band"
    },
    {
      "id": "72c0f663e8469dd36187ee05c02711f6",
      "bandId": "d95995a43e371aec2c7f4df40f7fdc42",
      "locationId": "a4df6f5c5655dd443bdaa2ac28ec6105",
      "date": "2025-06-09",
      "startTime": "17:50",
      "category": "band"
    },
    {
      "id": "214105d4ee381ab25d580b8ab986782e",
      "bandId": "065266d69f062ec2f65000fbc443babb",
      "locationId": "a4df6f5c5655dd443bdaa2ac28ec6105",
      "date": "2025-06-09",
      "startTime": "19:10",
      "category": "band"
    },
    {
      "id": "f1a1b6682b4107cbd0c1ee78f6567be9",
      "bandId": "2369803b80bf00925dbfdae202d393e7",
      "locationId": "a4df6f5c5655dd443bdaa2ac28ec6105",
      "date": "2025-06-09",
      "startTime": "20:50",
      "category": "band"
    },
    {
      "id": "62e06713685e2ea6a7ce1865a2fcff90",
      "bandId": "ffc59bd768d00cc390ee33007833eb81",
      "locationId": "a4df6f5c5655dd443bdaa2ac28ec6105",
      "date": "2025-06-09",
      "startTime": "22:30",
      "category": "band"
    },
    {
      "id": "ddd690cb5451cff7e547d5e4836f5c8a",
      "bandId": "ff332e46405212a70a15eb2e5b4037b4",
      "locationId": "2a55f3eca82c7bfb32506bcf7d3c1561",
      "date": "2025-06-09",
      "startTime": "18:45",
      "category": "band"
    },
    {
      "id": "bdc8a8c6f2be0f8c988f70aa59582477",
      "bandId": "293f2bd2a800eb08f306b43506383b4d",
      "locationId": "2a55f3eca82c7bfb32506bcf7d3c1561",
      "date": "2025-06-09",
      "startTime": "21:15",
      "category": "band"
    },
    {
      "id": "0a3fbec71ba466c145f8fa84691b39af",
      "bandId": "1c72dac6197c1660c719c4ecad7d74f0",
      "locationId": "f9de432063e814bcb67ea92bf3713fdb",
      "date": "2025-06-09",
      "startTime": "17:30",
      "category": "band"
    },
    {
      "id": "33a7b9a38a52358b41c370d3b0df9aff",
      "bandId": "b411aa827c064877860f16c3cdc3d1b9",
      "locationId": "f9de432063e814bcb67ea92bf3713fdb",
      "date": "2025-06-09",
      "startTime": "20:00",
      "category": "band"
    },
    {
      "id": "9ed56cf151fe31ee6ea1205255832e3e",
      "bandId": "1d518b7c2e383a766be63bf35fb3152d",
      "locationId": "f9de432063e814bcb67ea92bf3713fdb",
      "date": "2025-06-09",
      "startTime": "22:30",
      "category": "band"
    },
    {
      "id": "f6baa044f9e96d217525af7ef2cadd3c",
      "bandId": "ab95492f5a66c1557125e384f2cee6bd",
      "locationId": "5fe101bcd2edae028474473e52b9751f",
      "date": "2025-06-09",
      "startTime": "13:00",
      "category": "show"
    },
    {
      "id": "9ee33580186b803d2329d0671f04bdcc",
      "bandId": "ed482c72dc88d7297d3ce61f7a2d3742",
      "locationId": "5fe101bcd2edae028474473e52b9751f",
      "date": "2025-06-09",
      "startTime": "14:00",
      "category": "show"
    },
    {
      "id": "bfddddc06cd1bb017baa149533265760",
      "bandId": "b25a5bcb86cc022de45ceda74d518782",
      "locationId": "5fe101bcd2edae028474473e52b9751f",
      "date": "2025-06-09",
      "startTime": "14:30",
      "category": "show"
    },
    {
      "id": "eaa2dfef45ea3cf34affb8cd5baec379",
      "bandId": "c63728ab1da64d43804195dc96a86037",
      "locationId": "5fe101bcd2edae028474473e52b9751f",
      "date": "2025-06-09",
      "startTime": "15:30",
      "category": "show"
    },
    {
      "id": "533374d09de26ab7964d313c1792cf0b",
      "bandId": "ab95492f5a66c1557125e384f2cee6bd",
      "locationId": "5fe101bcd2edae028474473e52b9751f",
      "date": "2025-06-09",
      "startTime": "16:30",
      "category": "show"
    },
    {
      "id": "99b8f2366ab0a3e14975fc6d434b8b86",
      "bandId": "62b1a15d39a5fc95e1fa28b2af2f10ba",
      "locationId": "5fe101bcd2edae028474473e52b9751f",
      "date": "2025-06-09",
      "startTime": "17:30",
      "category": "show"
    },
    {
      "id": "735f3494dc88826379ac350e08752fbc",
      "bandId": "6cc0c9b8482b9d099c84caa8c72ffc40",
      "locationId": "5fe101bcd2edae028474473e52b9751f",
      "date": "2025-06-09",
      "startTime": "18:30",
      "category": "show"
    }
  ]
}